{
  "settings": {
    "languageSettings": "ഭാഷാ ക്രമീകരണങ്ങൾ",
    "language": "ഭാഷ",
    "generalSettings": "പൊതു ക്രമീകരണങ്ങൾ",
    "notificationSettings": "അറിയിപ്പ് ക്രമീകരണങ്ങൾ",
    "privacySettings": "സ്വകാര്യത ക്രമീകരണങ്ങൾ",
    "darkMode": "ഡാർക്ക് മോഡ്",
    "soundEffects": "ശബ്ദ ഇഫക്റ്റുകൾ",
    "emailAlerts": "ഇമെയിൽ അലേർട്ടുകൾ",
    "smsAlerts": "SMS അലേർട്ടുകൾ",
    "dataRetention": "ഡാറ്റ നിലനിർത്തൽ",
    "accountDeletion": "അക്കൗണ്ട് ഇല്ലാതാക്കൽ"
  },
  "nav": {
    "ward": "വാർഡ്",
    "profile": "പ്രൊഫൈൽ",
    "home": "ഹോം",
    "complaints": "പരാതികൾ",
    "myComplaints": "എന്റെ പരാതികൾ",
    "trackStatus": "നില ട്രാക്ക് ചെയ്യുക",
    "reports": "റിപ്പോർട്ടുകൾ",
    "users": "ഉപയോക്താക്കൾ",
    "dashboard": "ഡാഷ്ബോർഡ്",
    "maintenance": "പരിചരണം",
    "settings": "ക്രമീകരണങ്ങൾ",
    "logout": "ലോഗൗട്ട്",
    "login": "ലോഗിൻ",
    "register": "രജിസ്റ്റർ",
    "switchRole": "പങ്ക് മാറ്റുക"
  },
  "common": {
    "submit": "സമർപ്പിക്കുക",
    "cancel": "റദ്ദാക്കുക",
    "edit": "തിരുത്തുക",
    "delete": "ഇല്ലാതാക്കുക",
    "save": "സംരക്ഷിക്കുക",
    "close": "അടയ്ക്കുക",
    "view": "കാണുക",
    "search": "തിരയുക",
    "filter": "ഫിൽറ്റർ",
    "loading": "ലോഡ് ചെയ്യുന്നു...",
    "error": "പിശക്",
    "success": "വിജയം",
    "warning": "മുന്നറിയിപ്പ്",
    "info": "വിവരം",
    "confirm": "സ്ഥിരീകരിക്കുക",
    "yes": "അതെ",
    "no": "ഇല്ല",
    "next": "അടുത്തത്",
    "retry": "വീണ്ടും ശ്രമിക്കുക",
    "refresh": "പുതുക്കുക",
    "details": "വിശദാംശങ്ങൾ",
    "previous": "മുൻപത്തെ",
    "page": "താൾ",
    "of": "ൽ",
    "total": "ആകെ",
    "items": "ഇനങ്ങൾ",
    "noData": "ഡാറ്റ ഒന്നും ലഭ്യമല്ല",
    "selectAll": "എല്ലാം തിരഞ്ഞെടുക്കുക",
    "clear": "വൃത്തിയാക്കുക",
    "download": "ഡൗൺലോഡ്",
    "upload": "അപ്‌ലോഡ്",
    "required": "ആവശ്യമാണ്",
    "export": "എക്സ്പോർട്ട്",
    "optional": "ഐച്ഛികം",
    "status": "സ്ഥിതി",
    "priority": "പ്രാധാന്യം",
    "type": "തരം",
    "date": "തീയതി",
    "time": "സമയം",
    "name": "പേര്",
    "email": "ഇമെയിൽ",
    "phone": "ഫോൺ",
    "address": "വിലാസം",
    "description": "വിവരണം",
    "actions": "നടപടികൾ",
    "welcome": "സ്വാഗതം",
    "back": "തിരികെ",
    "continue": "തുടരുക",
    "finish": "പൂർത്തിയാക്കുക",
    "skip": "ഒഴിവാക്കുക",
    "help": "സഹായം",
    "support": "പിന്തുണ",
    "contact": "ബന്ധപ്പെടുക",
    "about": "കുറിച്ച്",
    "version": "പതിപ്പ്",
    "settings": "ക്രമീകരണങ്ങൾ",
    "preferences": "മുൻഗണനകൾ",
    "profile": "പ്രൊഫൈൽ",
    "account": "അക്കൗണ്ട്",
    "logout": "ലോഗൗട്ട്",
    "signin": "സൈൻ ഇൻ",
    "signup": "സൈൻ അപ്പ്",
    "register": "രജിസ്റ്റർ",
    "login": "ലോഗിൻ",
    "unknown": "അജ്ഞാതം",
    "notAvailable": "ലഭ്യമല്ല",
    "first": "ആദ്യത്തെ",
    "last": "അവസാനത്തെ",
    "more": "കൂടുതൽ",
    "unknownDate": "അജ്ഞാത തീയതി",
    "invalidDate": "അസാധുവായ തീയതി",
    "to": "വരെ"
  },
  "complaints": {
    "registerComplaint": "പരാതി രജിസ്റ്റർ ചെയ്യുക",
    "complaintId": "പരാതി ഐഡി",
    "complaintType": "പരാതിയുടെ തരം",
    "complaintStatus": "സ്ഥിതി",
    "complaintPriority": "പ്രാധാന്യം",
    "submittedBy": "സമർപ്പിച്ചത്",
    "assignedTo": "നിയോഗിച്ചത്",
    "submittedOn": "സമർപ്പിച്ച തീയതി",
    "resolvedOn": "പരിഹരിച്ച തീയതി",
    "deadline": "അവസാന തീയതി",
    "location": "സ്ഥലം",
    "ward": "വാർഡ്",
    "area": "പ്രദേശം",
    "landmark": "ലാൻഡ്മാർക്ക്",
    "contactInfo": "സമ്പർക്ക വിവരങ്ങൾ",
    "mobile": "മൊബൈൽ",
    "files": "ഫയലുകൾ",
    "remarks": "അഭിപ്രായങ്ങൾ",
    "feedback": "പ്രതികരണം",
    "rating": "റേറ്റിംഗ്",
    "comment": "അഭിപ്രായം",
    "slaStatus": "SLA നില",
    "timeElapsed": "കടന്നുപോയ സമയം",
    "escalationLevel": "എസ്കലേഷൻ ലെവൽ",
    "viewAndManageSubmitted": "നിങ്ങൾ സമർപ്പിച്ച പരാതികൾ കാണുകയും കൈകാര്യം ചെയ്യുകയും ചെയ്യുക",
    "manageAndTrackAll": "എല്ലാ പരാതികളും കൈകാര്യം ചെയ്യുകയും ട്രാക്ക് ചെയ്യുകയും ചെയ്യുക",
    "newComplaint": "പുതിയ പരാതി",
    "searchPlaceholder": "പരാതികൾ തിരയുക...",
    "searchTooltip": "പരാതി ഐഡി, വിവരണം, അല്ലെങ്കിൽ സ്ഥലം ഉപയോഗിച്ച് തിരയുക",
    "allStatus": "എല്ലാ സ്ഥിതികളും",
    "allPriority": "എല്ലാ പ്രാധാന്യവും",
    "highAndCritical": "ഉയർന്നതും ഗുരുതരവും",
    "allWards": "എല്ലാ വാർഡുകളും",
    "clearAllFilters": "എല്ലാ ഫിൽറ്ററുകളും മായ്ക്കുക",
    "refreshData": "ഡാറ്റ പുതുക്കുക",
    "subZone": "ഉപമേഖല",
    "allSubZones": "എല്ലാ ഉപമേഖലകളും",
    "allSLA": "എല്ലാ SLA",
    "needsAssignment": "അസൈൻമെന്റ് ആവശ്യമാണ്",
    "activeFilters": "സജീവ ഫിൽറ്ററുകൾ",
    "searchingFor": "തിരയുന്നു",
    "searchingInDescriptions": "വിവരണങ്ങളിലും സ്ഥലങ്ങളിലും തിരയുന്നു",
    "pleaseSignIn": "പരാതികൾ കാണാൻ ദയവായി സൈൻ ഇൻ ചെയ്യുക.",
    "failedToLoad": "പരാതികൾ ലോഡ് ചെയ്യുന്നതിൽ പരാജയപ്പെട്ടു",
    "noComplaintsFound": "പരാതികൾ കണ്ടെത്തിയില്ല",
    "tryAdjustingFilters": "നിങ്ങളുടെ ഫിൽറ്ററുകളോ തിരയൽ പദങ്ങളോ ക്രമീകരിക്കാൻ ശ്രമിക്കുക",
    "submitFirstComplaint": "ആരംഭിക്കാൻ നിങ്ങളുടെ ആദ്യ പരാതി സമർപ്പിക്കുക",
    "unknownType": "അജ്ഞാത തരം",
    "team": "ടീം",
    "officer": "ഓഫീസർ",
    "registeredOn": "രജിസ്റ്റർ ചെയ്ത തീയതി",
    "updated": "അപ്ഡേറ്റ് ചെയ്തത്",
    "closed": "അടച്ചത്",
    "rowsPerPage": "ഓരോ പേജിലും വരികൾ",
    "showing0of0": "0 ൽ 0 കാണിക്കുന്നു",
    "showing": "കാണിക്കുന്നു",
    "details": {
      "errorLoadingComplaint": "പരാതി ലോഡ് ചെയ്യുന്നതിൽ പിശക്",
      "failedToLoadDetails": "പരാതി വിശദാംശങ്ങൾ ലോഡ് ചെയ്യുന്നതിൽ പരാജയപ്പെട്ടു. ദയവായി വീണ്ടും ശ്രമിക്കുക.",
      "backToComplaints": "പരാതികളിലേക്ക് മടങ്ങുക",
      "complaintNotFound": "പരാതി കണ്ടെത്തിയില്ല",
      "complaintNotFoundMessage": "നിങ്ങൾ തിരയുന്ന പരാതി നിലവിലില്ല അല്ലെങ്കിൽ അത് കാണാൻ നിങ്ങൾക്ക് അനുമതിയില്ല.",
      "complaintTitle": "പരാതി",
      "created": "സൃഷ്ടിച്ചത്",
      "complaintDetails": "പരാതി വിശദാംശങ്ങൾ",
      "noDescriptionAvailable": "വിവരണം ലഭ്യമല്ല",
      "locationInformation": "സ്ഥല വിവരങ്ങൾ",
      "unknownArea": "അജ്ഞാത പ്രദേശം",
      "unknownWard": "അജ്ഞാത വാർഡ്",
      "noAddressProvided": "വിലാസം നൽകിയിട്ടില്ല",
      "timeline": "സമയരേഖ",
      "assigned": "നിയോഗിച്ചത്",
      "slaDeadline": "SLA സമയപരിധി",
      "resolutionTime": "പരിഹാര സമയം",
      "statusUpdates": "സ്ഥിതി അപ്ഡേറ്റുകൾ",
      "statusUpdatesAndComments": "സ്ഥിതി അപ്ഡേറ്റുകളും അഭിപ്രായങ്ങളും",
      "statusLabels": {
        "registered": "പരാതി രജിസ്റ്റർ ചെയ്തു",
        "assigned": "പരാതി നിയോഗിച്ചു",
        "inProgress": "പ്രവർത്തനം പുരോഗതിയിൽ",
        "resolved": "പരാതി പരിഹരിച്ചു",
        "closed": "പരാതി അടച്ചു"
      },
      "citizenMessages": {
        "registered": "നിങ്ങളുടെ പരാതി വിജയകരമായി രജിസ്റ്റർ ചെയ്യുകയും അവലോകനത്തിലാണ്.",
        "assigned": "നിങ്ങളുടെ പരാതി പരിഹാരത്തിനായി ഞങ്ങളുടെ പരിപാലന ടീമിന് നിയോഗിച്ചിരിക്കുന്നു.",
        "inProgress": "ഞങ്ങളുടെ ടീം നിങ്ങളുടെ പരാതി പരിഹരിക്കുന്നതിൽ സജീവമായി പ്രവർത്തിക്കുന്നു.",
        "resolved": "നിങ്ങളുടെ പരാതി പരിഹരിച്ചു. ദയവായി സ്ഥിരീകരിച്ച് ഫീഡ്ബാക്ക് നൽകുക.",
        "closed": "നിങ്ങളുടെ പരാതി പൂർത്തിയാക്കി അടച്ചിരിക്കുന്നു.",
        "statusUpdated": "നിങ്ങളുടെ പരാതിയുടെ സ്ഥിതി അപ്ഡേറ്റ് ചെയ്തു"
      },
      "noComment": "അഭിപ്രായമില്ല",
      "statusChangedFrom": "സ്ഥിതി മാറ്റി",
      "noUpdatesYet": "നിങ്ങളുടെ പരാതിക്ക് ഇതുവരെ അപ്ഡേറ്റുകൾ ലഭ്യമല്ല",
      "noStatusUpdates": "സ്ഥിതി അപ്ഡേറ്റുകൾ ലഭ്യമല്ല",
      "administrativeInformation": "ഭരണപരമായ വിവരങ്ങൾ",
      "assignmentDetails": "അസൈൻമെന്റ് വിശദാംശങ്ങൾ",
      "noEmail": "ഇമെയിലില്ല",
      "wardOfficer": "വാർഡ് ഓഫീസർ",
      "maintenanceTeam": "പരിപാലന ടീം",
      "resolvedBy": "പരിഹരിച്ചത്",
      "technicalDetails": "സാങ്കേതിക വിശദാംശങ്ങൾ",
      "tags": "ടാഗുകൾ",
      "lastUpdated": "അവസാനം അപ്ഡേറ്റ് ചെയ്തത്",
      "citizenFeedback": "പൗര ഫീഡ്ബാക്ക്",
      "internalRemarks": "ആന്തരിക അഭിപ്രായങ്ങൾ",
      "quickActions": "വേഗത്തിലുള്ള പ്രവർത്തനങ്ങൾ",
      "updateStatus": "സ്ഥിതി അപ്ഡേറ്റ് ചെയ്യുക",
      "provideFeedback": "ഫീഡ്ബാക്ക് നൽകുക",
      "complaintSubmitter": "പരാതി സമർപ്പിച്ചയാൾ",
      "registeredUser": "രജിസ്റ്റർ ചെയ്ത ഉപയോക്താവ്",
      "noPhoneProvided": "ഫോൺ നൽകിയിട്ടില്ല",
      "userPhone": "ഉപയോക്താവിന്റെ ഫോൺ",
      "notProvided": "നൽകിയിട്ടില്ല",
      "noEmailProvided": "ഇമെയിൽ നൽകിയിട്ടില്ല",
      "userEmail": "ഉപയോക്താവിന്റെ ഇമെയിൽ",
      "anonymousComplaint": "അജ്ഞാത പരാതി",
      "assignmentAndStatusInfo": "അസൈൻമെന്റും സ്ഥിതി വിവരങ്ങളും",
      "notAssigned": "അസൈൻ ചെയ്തിട്ടില്ല",
      "assignedOn": "അസൈൻ ചെയ്തത്",
      "unassigned": "അസൈൻ ചെയ്തിട്ടില്ല",
      "slaTimeline": "SLA സമയരേഖ",
      "priorityLevel": "മുൻഗണനാ തലം",
      "unknownPriority": "അജ്ഞാത മുൻഗണന",
      "maintenancePhotos": "പരിപാലന ഫോട്ടോകൾ",
      "unknownFile": "അജ്ഞാത ഫയൽ",
      "uploadedBy": "അപ്‌ലോഡ് ചെയ്തത്",
      "note": "കുറിപ്പ്",
      "noDescription": "വിവരണമില്ല",
      "preview": "പ്രിവ്യൂ",
      "complaintAttachments": "പരാതി അറ്റാച്ച്മെന്റുകൾ",
      "document": "രേഖ",
      "unknownSize": "അജ്ഞാത വലുപ്പം"
    },
    "types": {
      "Water_Supply": "ജലവിതരണം",
      "Electricity": "വൈദ്യുതി",
      "Road_Repair": "റോഡ് റിപ്പയർ",
      "Garbage_Collection": "മാലിന്യ ശേഖരണം",
      "Street_Lighting": "വീഥി ലൈറ്റിംഗ്",
      "Sewerage": "കാലുവ",
      "Public_Health": "പൊതു ആരോഗ്യം",
      "Traffic": "ഗതാഗതം",
      "Others": "മറ്റുള്ളവ"
    },
    "statuses": {
      "registered": "രജിസ്റ്റർ ചെയ്തു",
      "assigned": "നിയോഗിച്ചു",
      "in_progress": "പുരോഗമിക്കുന്നു",
      "resolved": "പരിഹരിച്ചു",
      "closed": "അടച്ചു",
      "reopened": "വീണ്ടും തുറന്നു"
    },
    "priorities": {
      "low": "കുറഞ്ഞത്",
      "medium": "ഇടത്തരം",
      "high": "ഉയർന്നത്",
      "critical": "ഗുരുതരമായത്"
    },
    "slaStatuses": {
      "ontime": "സമയം പാലിച്ചു",
      "warning": "മുന്നറിയിപ്പ്",
      "overdue": "കാലാവധി കഴിഞ്ഞു",
      "completed": "പൂർത്തിയായി"
    },
    "statusOverview": {
      "registered": "രജിസ്റ്റർ ചെയ്തു",
      "registeredSubtitle": "പുതുതായി രജിസ്റ്റർ ചെയ്തത്",
      "assigned": "അസൈൻ ചെയ്തു",
      "assignedSubtitle": "ടീമുകളിലേക്ക് അസൈൻ ചെയ്തത്",
      "inProgress": "പുരോഗമിക്കുന്നു",
      "inProgressSubtitle": "സജീവ പ്രവർത്തനം",
      "resolved": "പരിഹരിച്ചു",
      "resolvedSubtitle": "പരിഹരിച്ച പരാതികൾ",
      "reopened": "വീണ്ടും തുറന്നു",
      "reopenedSubtitle": "അടച്ചതിന് ശേഷം വീണ്ടും തുറന്നത്",
      "closed": "അടച്ചു",
      "closedSubtitle": "അടച്ച പരാതികൾ"
    },
    "widget": {
      "refresh": "പുതുക്കുക",
      "failedToLoad": "പരാതികൾ ലോഡ് ചെയ്യുന്നതിൽ പരാജയപ്പെട്ടു",
      "tryAgain": "വീണ്ടും ശ്രമിക്കുക",
      "noComplaintsFound": "പരാതികൾ കണ്ടെത്തിയില്ല",
      "noComplaintsMatchFilters": "തിരഞ്ഞെടുത്ത ഫിൽറ്ററുകളുമായി പരാതികൾ പൊരുത്തപ്പെടുന്നില്ല",
      "noComplaintsAvailable": "പരാതികൾ ലഭ്യമല്ല",
      "id": "ഐഡി",
      "description": "വിവരണം",
      "location": "സ്ഥലം",
      "status": "സ്ഥിതി",
      "priority": "മുൻഗണന",
      "team": "ടീം",
      "teamAssignment": "ടീം അസൈൻമെന്റ്",
      "rating": "റേറ്റിംഗ്",
      "sla": "എസ്എൽഎ",
      "closed": "അടച്ചു",
      "updated": "അപ്ഡേറ്റ് ചെയ്തു",
      "date": "തീയതി",
      "actions": "പ്രവർത്തനങ്ങൾ",
      "assigned": "അസൈൻ ചെയ്തു",
      "needsAssignment": "അസൈൻമെന്റ് ആവശ്യമാണ്",
      "notAssigned": "അസൈൻ ചെയ്തിട്ടില്ല",
      "unknownTeamMember": "അജ്ഞാത ടീം അംഗം"
    },
    "updateModal": {
      "title": "പരാതി അപ്ഡേറ്റ് ചെയ്യുക",
      "updateTaskStatus": "ടാസ്ക് സ്റ്റാറ്റസ് അപ്ഡേറ്റ് ചെയ്യുക",
      "manageComplaint": "പരാതി കൈകാര്യം ചെയ്യുക",
      "description": "പരാതിയുടെ സ്റ്റാറ്റസും അസൈൻമെന്റും അപ്ഡേറ്റ് ചെയ്യുക",
      "updateTaskDescription": "പരാതിക്കായി നിങ്ങളുടെ ജോലി സ്റ്റാറ്റസ് അപ്ഡേറ്റ് ചെയ്യുക",
      "manageComplaintDescription": "പരാതി അസൈൻ ചെയ്യുകയും കൈകാര്യം ചെയ്യുകയും ചെയ്യുക",
      "actingAs": "ആയി പ്രവർത്തിക്കുന്നു",
      "maintenancePermissions": "നിങ്ങൾക്ക് ജോലി സ്റ്റാറ്റസ് അപ്ഡേറ്റ് ചെയ്യാനും പ്രോഗ്രസ് നോട്ടുകൾ ചേർക്കാനും കഴിയും",
      "wardOfficerPermissions": "നിങ്ങൾക്ക് പരാതികൾ അസൈൻ ചെയ്യാനും അവയുടെ സ്റ്റാറ്റസ് കൈകാര്യം ചെയ്യാനും കഴിയും",
      "adminPermissions": "ഈ പരാതിയിൽ നിങ്ങൾക്ക് പൂർണ്ണ അഡ്മിനിസ്ട്രേറ്റീവ് നിയന്ത്രണമുണ്ട്",
      "limitedPermissions": "പരിമിതമായ അനുമതികൾ",
      "complaintSummary": "പരാതി സംഗ്രഹം",
      "currentAssignments": "നിലവിലെ അസൈൻമെന്റുകൾ",
      "wardOfficer": "വാർഡ് ഓഫീസർ",
      "complaintOversight": "പരാതി മേൽനോട്ടം",
      "maintenanceTeam": "മെയിന്റനൻസ് ടീം",
      "fieldWorkExecution": "ഫീൽഡ് വർക്ക് എക്സിക്യൂഷൻ",
      "assigned": "അസൈൻ ചെയ്തു",
      "notAssigned": "അസൈൻ ചെയ്തിട്ടില്ല",
      "needsAssignment": "അസൈൻമെന്റ് ആവശ്യമാണ്",
      "statusTransitionNotice": "സ്റ്റാറ്റസ് ട്രാൻസിഷൻ നോട്ടീസ്",
      "reopenTransitionMessage": "നിങ്ങൾ ഈ പരാതി വീണ്ടും തുറക്കുമ്പോൾ, അത് സ്വയമേവ ASSIGNED സ്റ്റാറ്റസിലേക്ക് മാറുകയും മെയിന്റനൻസ് ടീം അംഗത്തിന് പുനർഅസൈൻമെന്റ് ആവശ്യമാകുകയും ചെയ്യും।",
      "statusAndPriority": "സ്റ്റാറ്റസും മുൻഗണനയും",
      "status": "സ്റ്റാറ്റസ്",
      "priority": "മുൻഗണന",
      "setPriorityLevel": "പരാതി മുൻഗണന ലെവൽ സെറ്റ് ചെയ്യുക",
      "updateStatusNote": "നിങ്ങൾക്ക് സ്റ്റാറ്റസ് പ്രോഗ്രസിലേക്ക് അപ്ഡേറ്റ് ചെയ്യാനോ പരിഹരിച്ചതായി അടയാളപ്പെടുത്താനോ കഴിയും",
      "selectStatus": "സ്റ്റാറ്റസ് തിരഞ്ഞെടുക്കുക",
      "selectPriority": "മുൻഗണന തിരഞ്ഞെടുക്കുക",
      "statusLabels": {
        "registered": "രജിസ്റ്റർ ചെയ്തു",
        "assigned": "അസൈൻ ചെയ്തു",
        "inProgress": "പ്രോഗ്രസിൽ",
        "resolved": "പരിഹരിച്ചു",
        "closed": "അടച്ചു",
        "reopened": "വീണ്ടും തുറന്നു"
      },
      "priorityLabels": {
        "low": "കുറഞ്ഞ",
        "medium": "ഇടത്തരം",
        "high": "ഉയർന്ന",
        "critical": "ഗുരുതരമായ"
      },
      "priorityDescriptions": {
        "low": "അടിയന്തിരമല്ലാത്ത",
        "medium": "സ്റ്റാൻഡേർഡ്",
        "high": "അടിയന്തിരം",
        "critical": "അത്യാവശ്യം"
      },
      "assignmentRequired": "അസൈൻമെന്റ് ആവശ്യമാണ്",
      "assignmentRequiredMessage": "ഈ പരാതി മുന്നോട്ട് കൊണ്ടുപോകാൻ മെയിന്റനൻസ് ടീം അംഗത്തിന് അസൈൻ ചെയ്യേണ്ടതുണ്ട്।",
      "userAssignments": "ഉപയോക്തൃ അസൈൻമെന്റുകൾ",
      "adminControls": "അഡ്മിൻ നിയന്ത്രണങ്ങൾ",
      "selectWardOfficer": "വാർഡ് ഓഫീസർ തിരഞ്ഞെടുക്കുക",
      "selectMaintenanceTeam": "മെയിന്റനൻസ് ടീം തിരഞ്ഞെടുക്കുക",
      "selectMaintenanceTeamMember": "മെയിന്റനൻസ് ടീം അംഗത്തെ തിരഞ്ഞെടുക്കുക",
      "selectUser": "ഉപയോക്താവിനെ തിരഞ്ഞെടുക്കുക",
      "assignmentRequiredBadge": "അസൈൻമെന്റ് ആവശ്യമാണ്",
      "errorLoadingUsers": "ഉപയോക്താക്കളെ ലോഡ് ചെയ്യുന്നതിൽ പിശക്. ദയവായി വീണ്ടും ശ്രമിക്കുക.",
      "validationErrors": "ദയവായി ഇനിപ്പറയുന്ന പ്രശ്നങ്ങൾ പരിഹരിക്കുക:",
      "remarks": "അഭിപ്രായങ്ങൾ (ഓപ്ഷണൽ)",
      "workNotes": "വർക്ക് നോട്ടുകൾ (ഓപ്ഷണൽ)",
      "remarksPlaceholder": "ഈ അപ്ഡേറ്റിനെക്കുറിച്ച് എന്തെങ്കിലും അധിക കമന്റുകളോ അഭിപ്രായങ്ങളോ ചേർക്കുക...",
      "workNotesPlaceholder": "ജോലി പുരോഗതി, നേരിട്ട പ്രശ്നങ്ങൾ, അല്ലെങ്കിൽ പൂർത്തീകരണ വിശദാംശങ്ങൾ എന്നിവയെക്കുറിച്ചുള്ള കുറിപ്പുകൾ ചേർക്കുക...",
      "wardOfficerNotesPlaceholder": "അസൈൻമെന്റ്, നിർദ്ദേശങ്ങൾ, അല്ലെങ്കിൽ സ്റ്റാറ്റസ് മാറ്റങ്ങൾ എന്നിവയെക്കുറിച്ചുള്ള കുറിപ്പുകൾ ചേർക്കുക...",
      "workProgressNote": "ഭാവിയിലെ റഫറൻസിനായി നിങ്ങളുടെ ജോലി പുരോഗതിയും എന്തെങ്കിലും പ്രശ്നങ്ങളും ഡോക്യുമെന്റ് ചെയ്യുക",
      "contextNote": "പരാതി പരിഹാരത്തിൽ സഹായിക്കുന്ന സന്ദർഭമോ നിർദ്ദേശങ്ങളോ ചേർക്കുക",
      "cancel": "റദ്ദാക്കുക",
      "updateComplaint": "പരാതി അപ്ഡേറ്റ് ചെയ്യുക",
      "saveChanges": "മാറ്റങ്ങൾ സേവ് ചെയ്യുക",
      "updateStatus": "സ്റ്റാറ്റസ് അപ്ഡേറ്റ് ചെയ്യുക",
      "reopenComplaint": "പരാതി വീണ്ടും തുറക്കുക",
      "updating": "അപ്ഡേറ്റ് ചെയ്യുന്നു...",
      "reopening": "വീണ്ടും തുറക്കുന്നു...",
      "success": "വിജയം",
      "updateSuccessMessage": "പരാതി വിജയകരമായി അപ്ഡേറ്റ് ചെയ്തു. നിങ്ങൾക്ക് താഴെ അപ്ഡേറ്റ് ചെയ്ത അസൈൻമെന്റ് കാണാൻ കഴിയും.",
      "reopenSuccessMessage": "പരാതി വിജയകരമായി വീണ്ടും തുറന്നു. ഇത് ASSIGNED സ്റ്റാറ്റസിലേക്ക് സെറ്റ് ചെയ്യുകയും പുനർഅസൈൻമെന്റ് ആവശ്യമാകുകയും ചെയ്തു.",
      "error": "പിശക്",
      "updateFailedMessage": "പരാതി അപ്ഡേറ്റ് ചെയ്യുന്നതിൽ പരാജയപ്പെട്ടു",
      "validationMessages": {
        "statusPermissionDenied": "സ്റ്റാറ്റസ് '{{status}}' ആയി സെറ്റ് ചെയ്യാൻ നിങ്ങൾക്ക് അനുമതിയില്ല. ലഭ്യമായ ഓപ്ഷനുകൾ: {{options}}",
        "maintenanceCannotAssign": "മെയിന്റനൻസ് ടീമിന് സ്റ്റാറ്റസ് തിരികെ 'Assigned' ആയി സെറ്റ് ചെയ്യാൻ കഴിയില്ല.",
        "maintenanceCannotRegister": "മെയിന്റനൻസ് ടീമിന് സ്റ്റാറ്റസ് 'Registered' ആയി സെറ്റ് ചെയ്യാൻ കഴിയില്ല.",
        "maintenanceCannotChangePriority": "മെയിന്റനൻസ് ടീമിന് പരാതി മുൻഗണന മാറ്റാൻ കഴിയില്ല. ആവശ്യമെങ്കിൽ നിങ്ങളുടെ സൂപ്പർവൈസറെ ബന്ധപ്പെടുക.",
        "assignMaintenanceTeam": "സ്റ്റാറ്റസ് 'Assigned' ആയി സെറ്റ് ചെയ്യുന്നതിന് മുമ്പ് ദയവായി ഒരു മെയിന്റനൻസ് ടീം അംഗത്തെ അസൈൻ ചെയ്യുക.",
        "selectWardOfficer": "സ്റ്റാറ്റസ് 'Assigned' ആയി സെറ്റ് ചെയ്യുന്നതിന് മുമ്പ് ദയവായി ഒരു വാർഡ് ഓഫീസറെ തിരഞ്ഞെടുക്കുക.",
        "onlyAdminCanReopen": "അഡ്മിനിസ്ട്രേറ്റർമാർക്ക് മാത്രമേ പരാതികൾ വീണ്ടും തുറക്കാൻ കഴിയൂ.",
        "onlyClosedCanReopen": "അടച്ച പരാതികൾ മാത്രമേ വീണ്ടും തുറക്കാൻ കഴിയൂ.",
        "needsTeamAssignment": "ഈ പരാതിക്ക് മെയിന്റനൻസ് ടീം അസൈൻമെന്റ് ആവശ്യമാണ്. ദയവായി ഒരു ടീം അംഗത്തെ തിരഞ്ഞെടുക്കുക."
      },
      "debugInfo": "ഡീബഗ് വിവരങ്ങൾ"
    }
  },
  "auth": {
    "login": "ലോഗിൻ",
    "signUp": "സൈൻ അപ്പ്",
    "register": "രജിസ്റ്റർ",
    "logout": "ലോഗൗട്ട്",
    "email": "ഇമെയിൽ വിലാസം",
    "password": "പാസ്വേഡ്",
    "confirmPassword": "പാസ്വേഡ് സ്ഥിരീകരിക്കുക",
    "forgotPassword": "പാസ്വേഡ് മറന്നോ",
    "resetPassword": "പാസ്വേഡ് റീസെറ്റ്",
    "profile": "പ്രൊഫൈൽ",
    "updateProfile": "പ്രൊഫൈൽ അപ്ഡേറ്റ് ചെയ്യുക",
    "changePassword": "പാസ്വേഡ് മാറ്റുക",
    "currentPassword": "നിലവിലെ പാസ്വേഡ്",
    "newPassword": "പുതിയ പാസ്വേഡ്",
    "fullName": "പൂർണ്ണ പേര്",
    "phoneNumber": "ഫോൺ നമ്പർ",
    "role": "പങ്ക്",
    "ward": "വാർഡ്",
    "department": "വകുപ്പ്",
    "language": "ഭാഷ",
    "notifications": "അറിയിപ്പുകൾ",
    "emailAlerts": "ഇമെയിൽ അലർട്ടുകൾ",
    "avatar": "അവതാരം",
    "lastLogin": "അവസാന ലോഗിൻ",
    "joinedOn": "ചേർന്നത്",
    "accountStatus": "അക്കൗണ്ട് നില",
    "active": "സജീവം",
    "inactive": "നിഷ്‌ക്രിയം",
    "passwordNotSet": "നിങ്ങളുടെ പാസ്‌വേഡ് സജ്ജീകരിച്ചിട്ടില്ല. നിങ്ങൾക്ക് കഴിയും:",
    "emailPlaceholder": "നിങ്ങളുടെ ഇമെയിൽ നൽകുക",
    "signingIn": "സൈൻ ഇൻ ചെയ്യുന്നു...",
    "roles": {
      "citizen": "പൗരൻ",
      "admin": "അഡ്മിനിസ്ട്രേറ്റർ",
      "ward_officer": "വാർഡ് ഓഫീസർ",
      "maintenance": "പരിചരണ ടീം"
    }
  },
  "guest": {
    "guestSubmission": "അതിഥി സമർപ്പണം",
    "registeredUser": "രജിസ്റ്റർ ചെയ്ത ഉപയോക്താവ്",
    "emailVerification": "ഇമെയിൽ സ്ഥിരീകരണം",
    "otpSent": "OTP അയച്ചു",
    "otpVerification": "OTP സ്ഥിരീകരണം",
    "verifyAndSubmit": "സ്ഥിരീകരിച്ച് സമർപ്പിക്കുക",
    "sendOtpAndSubmit": "OTP അയച്ചു സമർപ്പിക്കുക",
    "trackComplaint": "പരാതി ട്രാക്ക് ചെയ്യുക",
    "guestSubmissionProcess": "അതിഥി സമർപ്പണ പ്രക്രിയ",
    "guestSubmissionDescription": "അതിഥി ഉപയോക്താക്കൾക്കായി, ഞങ്ങൾ നിങ്ങളുടെ ഇമെയിലിലേക്ക് OTP അയയ്ക്കും. ഇത് നിങ്ങളുടെ പരാതിയുടെ വിശ്വാസ്യത ഉറപ്പാക്കുന്നു, പിന്നീട് ട്രാക്ക് ചെയ്യാനും സഹായിക്കുന്നു.",
    "welcomeBack": "തിരിച്ചു വരവിന് സ്വാഗതം",
    "loginRequired": "ലോഗിൻ ആവശ്യമാണ്",
    "loginRequiredDescription": "രജിസ്റ്റർ ചെയ്ത ഉപയോക്താവായി പരാതി സമർപ്പിക്കാൻ ദയവായി ലോഗിൻ ചെയ്യുക അല്ലെങ്കിൽ രജിസ്റ്റർ ചെയ്യുക.",
    "enterOtp": "6-അക്ക OTP നൽകുക",
    "resendOtp": "വീണ്ടും അയയ്ക്കുക",
    "otpExpires": "OTP കാലഹരണപ്പെടും",
    "otpInstructions": "ഞങ്ങൾ നിങ്ങളുടെ ഇമെയിലിലേക്ക് 6-അക്ക OTP അയച്ചു. ദയവായി അത് താഴെ നൽകുക.",
    "checkEmail": "നിങ്ങളുടെ ഇമെയിൽ ഇൻബോക്‌സ്, സ്പാം ഫോൾഡർ പരിശോധിക്കുക",
    "recentComplaints": "നിങ്ങളുടെ അടുത്തിടെ നൽകിയ പരാതികൾ",
    "complaintDetails": "പരാതിയുടെ വിശദാംശങ്ങൾ",
    "nextSteps": "അടുത്ത ചുവടുകൾ",
    "supportContact": "സഹായം വേണോ?"
  },
  "index": {
    "title": "പരാതി മാനേജ്മെന്റ് പോർട്ടൽ",
    "subtitle": "പരാതി മാനേജ്മെന്റ് സിസ്റ്റത്തിലേക്ക് സ്വാഗതം. പൗര പ്രശ്നങ്ങൾ സമർപ്പിക്കുക, പുരോഗതി ട്രാക്ക് ചെയ്യുക, മികച്ച നഗരം കെട്ടിപ്പടുക്കാൻ സഹായിക്കുക.",
    "heroTitle": "{{appName}} പോർട്ടൽ",
    "trackYourComplaint": "നിങ്ങളുടെ പരാതി ട്രാക്ക് ചെയ്യുക",
    "complaintIdPlaceholder": "നിങ്ങളുടെ പരാതി ഐഡി നൽകുക (ഉദാ., {{example}})",
    "verifyAndTrack": "സ്ഥിരീകരിച്ച് ട്രാക്ക് ചെയ്യുക",
    "sending": "അയയ്ക്കുന്നു...",
    "keyFeatures": "പ്രധാന സവിശേഷതകൾ",
    "realTimeTracking": "തത്സമയ ട്രാക്കിംഗ്",
    "realTimeTrackingDesc": "തൽക്ഷണ അപ്‌ഡേറ്റുകൾക്കൊപ്പം പരാതി പുരോഗതി തത്സമയം നിരീക്ഷിക്കുക",
    "quickRegistration": "ദ്രുത പരാതി രജിസ്ട്രേഷൻ",
    "quickRegistrationDesc": "ടൈപ്പ്, ഫോട്ടോ, ലൊക്കേഷൻ എന്നിവ ഉപയോഗിച്ച് ഒരു മിനിറ്റിനുള്ളിൽ പ്രശ്നങ്ങൾ ലേഖപ്പെടുത്തുക",
    "emailAlerts": "ഇമെയിൽ അലേർട്ടുകൾ",
    "emailAlertsDesc": "രജിസ്ട്രേഷൻ മുതൽ പരിഹാരം വരെ ഓരോ ഘട്ടത്തിലും അറിയിപ്പ് ലഭിക്കുക",
    "multilingualSupport": "ബഹുഭാഷാ പിന്തുണ",
    "multilingualSupportDesc": "ഇംഗ്ലീഷ്, മലയാളം, ഹിന്ദി എന്നിവയിൽ ലഭ്യമാണ്"
  },
  "forms": {
    "contactInformation": "സമ്പർക്ക വിവരങ്ങൾ",
    "problemDetails": "പ്രശ്നത്തിന്റെ വിശദാംശങ്ങൾ",
    "locationDetails": "സ്ഥലത്തിന്റെ വിശദാംശങ്ങൾ",
    "complaintDescription": "പരാതിയുടെ വിവരണം",
    "optionalUploads": "ഐച്ഛിക അപ്‌ലോഡുകൾ",
    "captchaVerification": "ക്യാപ്ച്ച സ്ഥിരീകരണം",
    "enterCaptcha": "മുകളിൽ കാണിച്ചിരിക്കുന്ന കോഡ് നൽകുക",
    "resetForm": "ഫോം റീസെറ്റ് ചെയ്യുക",
    "submitComplaint": "പരാതി സമർപ്പിക്കുക",
    "complaintSubmitted": "പരാതി വിജയകരമായി സമർപ്പിച്ചു!",
    "complaintSubmissionError": "പരാതി സമർപ്പിക്കൽ പരാജയപ്പെട്ടു",
    "fileUploadError": "ഫയൽ അപ്‌ലോഡ് പരാജയപ്പെട്ടു",
    "invalidCaptcha": "അസാധുവായ ക്യാപ്ച്ച കോഡ്",
    "requiredField": "ഈ ഫീൽഡ് ആവശ്യമാണ്",
    "invalidEmail": "അസാധുവായ ഇമെയിൽ വിലാസം",
    "invalidPhone": "അസാധുവായ ഫോൺ നമ്പർ",
    "minCharacters": "കുറഞ്ഞത് 3 അക്ഷരങ്ങൾ ആവശ്യമാണ്"
  },
  "dashboard": {
    "overview": "അവലോകനം",
    "statistics": "സ്ഥിതിവിവരക്കണക്ക്",
    "recentComplaints": "അടുത്തിടെ നൽകിയ പരാതികൾ",
    "pendingTasks": "ലമ്പിച്ചിരിക്കുന്ന ജോലികൾ",
    "slaCompliance": "SLA അനുസരണം",
    "performanceMetrics": "പ്രവർത്തന മീട്രിക്‌സ്",
    "quickActions": "വേഗത്തിലുള്ള പ്രവർത്തനങ്ങൾ",
    "notifications": "അറിയിപ്പുകൾ",
    "alerts": "മുന്നറിയിപ്പുകൾ",
    "reports": "റിപ്പോർട്ടുകൾ",
    "analytics": "വിശകലനം",
    "trends": "പ്രവണതകൾ",
    "insights": "അന്തര്ദൃഷ്ടി",
    "system": "സിസ്റ്റം",
    "loadingDashboardData": "ഡാഷ്ബോർഡ് ഡാറ്റ ലോഡ് ചെയ്യുന്നു...",
    "activeUsers": "സജീവ ഉപയോക്താക്കൾ",
    "satisfaction": "സംതൃപ്തി",
    "complaintTrends": "പരാതി പ്രവണതകൾ (കഴിഞ്ഞ 6 മാസം)",
    "complaintsByType": "തരം അനുസരിച്ച് പരാതികൾ",
    "performanceSummary": "പ്രവർത്തന സംഗ്രഹം",
    "userManagement": "ഉപയോക്തൃ മാനേജ്മെന്റ്",
    "systemConfiguration": "സിസ്റ്റം കോൺഫിഗറേഷൻ",
    "systemHealth": "സിസ്റ്റം ആരോഗ്യം (തത്സമയം)",
    "overallComplaintsHeatmap": "മൊത്തത്തിലുള്ള പരാതി ഹീറ്റ്മാപ്",
    "complaintsByTypeAcrossWards": "വാർഡുകളിൽ തരം അനുസരിച്ച് പരാതികൾ (അവലോകനം)",
    "complaintType": "പരാതിയുടെ തരം",
    "ward": "വാർഡ്",
    "noComplaintTrendData": "പരാതി പ്രവണത ഡാറ്റ ലഭ്യമല്ല",
    "noComplaintTypeData": "പരാതി തരം ഡാറ്റ ലഭ്യമല്ല",
    "noRecentActivity": "അടുത്തിടെയുള്ള പ്രവർത്തനം ലഭ്യമല്ല",
    "complaints": "പരാതികൾ",
    "resolved": "പരിഹരിച്ചു",
    "citizenFeedback": "പൗര പ്രതികരണം",
    "target": "ലക്ഷ്യം",
    "aboveTarget": "ലക്ഷ്യത്തിന് മുകളിൽ",
    "belowTarget": "ലക്ഷ്യത്തിന് താഴെ",
    "overallResolutionRate": "മൊത്തത്തിലുള്ള പരിഹാര നിരക്ക്",
    "averageResolutionTime": "ശരാശരി പരിഹാര സമയം",
    "satisfactionScore": "സംതൃപ്തി സ്കോർ",
    "detailedReports": "വിശദമായ റിപ്പോർട്ടുകൾ",
    "addUser": "ഉപയോക്താവിനെ ചേർക്കുക",
    "manageUsers": "ഉപയോക്താക്കളെ മാനേജ് ചെയ്യുക",
    "wardOfficers": "വാർഡ് ഓഫീസർമാർ",
    "maintenanceTeam": "പരിചരണ ടീം",
    "userActivity": "ഉപയോക്തൃ പ്രവർത്തനം (തത്സമയം)",
    "loadingActivity": "പ്രവർത്തനം ലോഡ് ചെയ്യുന്നു...",
    "failedToLoadUserActivity": "ഉപയോക്തൃ പ്രവർത്തനം ലോഡ് ചെയ്യുന്നതിൽ പരാജയപ്പെട്ടു",
    "activeUsers24h": "സജീവ ഉപയോക്താക്കൾ (24 മണിക്കൂർ)",
    "newRegistrations24h": "പുതിയ രജിസ്ട്രേഷനുകൾ (24 മണിക്കൂർ)",
    "loginSuccessRate": "ലോഗിൻ വിജയ നിരക്ക്",
    "recentActivity": "അടുത്തിടെയുള്ള പ്രവർത്തനം",
    "systemSettings": "സിസ്റ്റം ക്രമീകരണങ്ങൾ",
    "wardManagement": "വാർഡ് മാനേജ്മെന്റ്",
    "complaintTypes": "പരാതി തരങ്ങൾ",
    "checkingHealth": "ആരോഗ്യം പരിശോധിക്കുന്നു...",
    "failedToLoadSystemHealth": "സിസ്റ്റം ആരോഗ്യം ലോഡ് ചെയ്യുന്നതിൽ പരാജയപ്പെട്ടു",
    "applicationUptime": "ആപ്ലിക്കേഷൻ അപ്ടൈം",
    "databaseStatus": "ഡാറ്റാബേസ് നില",
    "emailService": "ഇമെയിൽ സേവനം",
    "healthy": "ആരോഗ്യകരം",
    "unhealthy": "അനാരോഗ്യകരം",
    "operational": "പ്രവർത്തനക്ഷമം",
    "unknown": "അജ്ഞാതം",
    "loadingHeatmap": "ഹീറ്റ്മാപ് ലോഡ് ചെയ്യുന്നു...",
    "onTarget": "ലക്ഷ്യത്തിൽ",
    "needsImprovement": "മെച്ചപ്പെടുത്തൽ ആവശ്യം",
    "good": "നല്ലത്",
    "belowTarget": "ലക്ഷ്യത്തിന് താഴെ",
    "excellent": "മികച്ചത്",
    "notAvailable": "ലഭ്യമല്ല",
    "admin": {
      "title": "അഡ്മിനിസ്ട്രേറ്റർ ഡാഷ്ബോർഡ്",
      "subtitle": "പൂർണ്ണ സിസ്റ്റം അവലോകനവും മാനേജ്മെന്റ് നിയന്ത്രണങ്ങളും",
      "activeComplaints": "സജീവ പരാതികൾ",
      "overdueComplaints": "കാലാവധി കഴിഞ്ഞ ജോലികൾ",
      "pendingAssignments": "ലംബിച്ചിരിക്കുന്ന ടീം അസൈൻമെന്റ്",
      "avgResolution": "ശരാശരി പരിഹാരം",
      "systemHealth": "സിസ്റ്റം ആരോഗ്യം",
      "recentActivity": "അടുത്തിടെയുള്ള സിസ്റ്റം പ്രവർത്തനം",
      "loadingData": "ഡാഷ്ബോർഡ് ഡാറ്റ ലോഡ് ചെയ്യുന്നു...",
      "dataLoadError": "ചില ഡാഷ്ബോർഡ് ഡാറ്റ ലോഡ് ചെയ്യുന്നതിൽ പരാജയപ്പെട്ടു",
      "overviewHeatmap": "അവലോകന ഹീറ്റ്മാപ്",
      "responseTime": "പ്രതികരണ സമയം",
      "resolutionRate": "പരിഹാര നിരക്ക്",
      "satisfactionScore": "സംതൃപ്തി സ്കോർ",
      "pendingResolution": "പരിഹാരം ലംബിച്ചിരിക്കുന്നു",
      "openPastDeadline": "അവസാന തീയതി കഴിഞ്ഞ് തുറന്നിരിക്കുന്നു",
      "needsMaintenanceAssignment": "പരിചരണ അസൈൻമെന്റ് ആവശ്യമാണ്",
      "averageClosureTime": "ശരാശരി അടയ്ക്കൽ സമയം",
      "slaBreaches": "SLA ലംഘനങ്ങൾ (തുറന്നത് + വൈകി പരിഹരിച്ചത്)",
      "overviewHeatmapDesc": "വാർഡുകളിലും തരങ്ങളിലുമായി പരാതികളുടെ ഉയർന്ന തലത്തിലുള്ള കാഴ്ച"
    },
    "citizen": {
      "welcome": "തിരിച്ചുവരവിന് സ്വാഗതം, {{name}}!",
      "subtitle": "നിങ്ങളുടെ പരാതികൾ ട്രാക്ക് ചെയ്യുകയും ഏറ്റവും പുതിയ പുരോഗതിയുമായി അപ്ഡേറ്റ് ചെയ്യുകയും ചെയ്യുക",
      "totalComplaints": "ആകെ പരാതികൾ",
      "allTimeSubmissions": "എല്ലാ സമയത്തെയും സമർപ്പണങ്ങൾ",
      "pending": "ലംബിച്ചിരിക്കുന്നു",
      "awaitingAssignment": "അസൈൻമെന്റിനായി കാത്തിരിക്കുന്നു",
      "inProgress": "പുരോഗമിക്കുന്നു",
      "beingWorkedOn": "പ്രവർത്തിക്കുന്നു",
      "resolved": "പരിഹരിച്ചു",
      "successfullyResolved": "വിജയകരമായി പരിഹരിച്ചു",
      "resolutionProgress": "പരിഹാര പുരോഗതി",
      "overallResolutionRate": "മൊത്തത്തിലുള്ള പരിഹാര നിരക്ക്",
      "avgResolutionTime": "ശരാശരി പരിഹാര സമയം",
      "myComplaints": "എന്റെ പരാതികൾ",
      "newComplaint": "പുതിയ പരാതി",
      "searchPlaceholder": "ID, വിവരണം, അല്ലെങ്കിൽ സ്ഥലം ഉപയോഗിച്ച് തിരയുക...",
      "allStatus": "എല്ലാ സ്ഥിതിയും",
      "allTypes": "എല്ലാ തരങ്ങളും",
      "sortBy": "ഇതിനനുസരിച്ച് ക്രമീകരിക്കുക",
      "newestFirst": "ഏറ്റവും പുതിയത് ആദ്യം",
      "oldestFirst": "ഏറ്റവും പഴയത് ആദ്യം",
      "highPriorityFirst": "ഉയർന്ന മുൻഗണന ആദ്യം",
      "clearFilters": "ഫിൽറ്ററുകൾ മായ്ക്കുക",
      "noComplaints": "പരാതികൾ കണ്ടെത്തിയില്ല",
      "noComplaintsMessage": "നിങ്ങൾ ഇതുവരെ പരാതികൾ സമർപ്പിച്ചിട്ടില്ല.",
      "submitFirstComplaint": "നിങ്ങളുടെ ആദ്യ പരാതി സമർപ്പിക്കുക",
      "quickActions": "വേഗത്തിലുള്ള പ്രവർത്തനങ്ങൾ",
      "submitNewComplaint": "പുതിയ പരാതി സമർപ്പിക്കുക",
      "viewAllComplaints": "എല്ലാ പരാതികളും കാണുക",
      "helpSupport": "സഹായവും പിന്തുണയും",
      "loadingComplaints": "പരാതികൾ ലോഡ് ചെയ്യുന്നു..."
    },
    "wardOfficer": {
      "title": "വാർഡ് ഓഫീസർ ഡാഷ്ബോർഡ്",
      "subtitle": "{{wardName}} ന്റെ പരാതികൾ കൈകാര്യം ചെയ്യുകയും ടീം പ്രകടനം നിരീക്ഷിക്കുകയും ചെയ്യുക",
      "manageComplaints": "{{wardName}} ന്റെ പരാതികൾ കൈകാര്യം ചെയ്യുകയും ടീം പ്രകടനം നിരീക്ഷിക്കുകയും ചെയ്യുക",
      "totalComplaints": "ആകെ പരാതികൾ",
      "allComplaintsInWard": "വാർഡിലെ എല്ലാ പരാതികളും",
      "filterByStatus": "സ്ഥിതി അനുസരിച്ച് ഫിൽറ്റർ ചെയ്യുക",
      "clearFilter": "ഫിൽറ്റർ മായ്ക്കുക",
      "additionalFilters": "അധിക ഫിൽറ്ററുകൾ",
      "overdue": "കാലാവധി കഴിഞ്ഞത്",
      "urgentPriority": "അടിയന്തിര മുൻഗണന",
      "clearAllFilters": "എല്ലാ ഫിൽറ്ററുകളും മായ്ക്കുക",
      "filteredComplaints": "ഫിൽറ്റർ ചെയ്ത പരാതികൾ",
      "recentComplaints": "അടുത്തിടെയുള്ള പരാതികൾ",
      "filteredResults": "ഫിൽറ്റർ ചെയ്ത ഫലങ്ങൾ",
      "viewAllInComplaintsPage": "പരാതി പേജിൽ എല്ലാം കാണുക",
      "quickActions": "വേഗത്തിലുള്ള പ്രവർത്തനങ്ങൾ",
      "assignNewComplaints": "പുതിയ പരാതികൾ അസൈൻ ചെയ്യുക",
      "handleUrgent": "അടിയന്തിരം കൈകാര്യം ചെയ്യുക",
      "assignToTeam": "ടീമിലേക്ക് അസൈൻ ചെയ്യുക",
      "generateReports": "റിപ്പോർട്ടുകൾ സൃഷ്ടിക്കുക",
      "overviewHeatmap": "അവലോകന ഹീറ്റ്മാപ്",
      "overviewHeatmapDesc": "നിങ്ങളുടെ വാർഡിലെ ഉപമേഖലകളിൽ പരാതികളുടെ വിതരണം",
      "wardOverviewHeatmap": "വാർഡ് അവലോകന ഹീറ്റ്മാപ്",
      "complaintsByType": "{{wardName}} ൽ തരം അനുസരിച്ച് പരാതികൾ",
      "loadingHeatmap": "ഹീറ്റ്മാപ് ലോഡ് ചെയ്യുന്നു...",
      "wardPerformance": "വാർഡ് പ്രകടനം",
      "completedWork": "പൂർത്തിയാക്കി",
      "active": "സജീവം",
      "loadingWardStatistics": "വാർഡ് സ്ഥിതിവിവരക്കണക്കുകൾ ലോഡ് ചെയ്യുന്നു...",
      "errorLoadingWardStatistics": "വാർഡ് സ്ഥിതിവിവരക്കണക്കുകൾ ലോഡ് ചെയ്യുന്നതിൽ പിശക്",
      "failedToLoadDashboardData": "ഡാഷ്ബോർഡ് ഡാറ്റ ലോഡ് ചെയ്യുന്നതിൽ പരാജയപ്പെട്ടു",
      "retry": "വീണ്ടും ശ്രമിക്കുക",
      "yourAssignedWard": "നിങ്ങളുടെ അസൈൻ ചെയ്ത വാർഡ്"
    }
  },
  "reports": {
    "title": "റിപ്പോർട്ടുകളും വിശകലനവും",
    "complaintReports": "പരാതി റിപ്പോർട്ടുകൾ",
    "performanceReports": "പ്രവർത്തന റിപ്പോർട്ടുകൾ",
    "slaReports": "SLA റിപ്പോർട്ടുകൾ",
    "userReports": "ഉപയോക്തൃ റിപ്പോർട്ടുകൾ",
    "wardReports": "വാർഡ് റിപ്പോർട്ടുകൾ",
    "typeReports": "തരം റിപ്പോർട്ടുകൾ",
    "statusReports": "സ്ഥിതി റിപ്പോർട്ടുകൾ",
    "dateRange": "തീയതി പരിധി",
    "from": "മുതൽ",
    "to": "വരെ",
    "generate": "റിപ്പോർട്ട് ജനറേറ്റ് ചെയ്യുക",
    "generating": "ജനറേറ്റ് ചെയ്യുന്നു...",
    "export": {
      "export": "എക്സ്പോർട്ട് ചെയ്യുക",
      "exportPdf": "PDF എക്സ്പോർട്ട് ചെയ്യുക",
      "exporting": "എക്സ്പോർട്ട് ചെയ്യുന്നു...",
      "permissionDenied": "ഡാറ്റ എക്സ്പോർട്ട് ചെയ്യാൻ നിങ്ങൾക്ക് അനുമതിയില്ല",
      "noDataAvailable": "എക്സ്പോർട്ടിനായി ഡാറ്റ ലഭ്യമല്ല",
      "noDataToExport": "എക്സ്പോർട്ട് ചെയ്യാൻ ഡാറ്റയില്ല",
      "stillLoading": "എക്സ്പോർട്ട് പ്രവർത്തനം ഇപ്പോഴും ലോഡ് ചെയ്യുന്നു. ദയവായി ഒരു നിമിഷം കഴിഞ്ഞ് വീണ്ടും ശ്രമിക്കുക.",
      "successful": "എക്സ്പോർട്ട് വിജയകരം",
      "successMessage": "{{format}} എക്സ്പോർട്ട് വിജയകരമായി പൂർത്തിയായി! നിങ്ങളുടെ ഡൗൺലോഡ് ഫോൾഡർ പരിശോധിക്കുക.",
      "failed": "എക്സ്പോർട്ട് പരാജയപ്പെട്ടു",
      "libraryError": "എക്സ്പോർട്ട് ലൈബ്രറി പിശക്",
      "libraryErrorMessage": "ഡെവലപ്മെന്റ് കാഷെ പ്രശ്നം കാരണം എക്സ്പോർട്ട് ലൈബ്രറി ലോഡ് ചെയ്യുന്നതിൽ പരാജയപ്പെട്ടു. പേജ് റിഫ്രഷ് ചെയ്യുക (Ctrl+F5) അല്ലെങ്കിൽ CSV എക്സ്പോർട്ട് ഉപയോഗിക്കുക.",
      "csvAlternative": "വിശ്വസനീയമായ ബദലായി CSV എക്സ്പോർട്ട് ഉപയോഗിക്കാൻ ശ്രമിക്കുക.",
      "csvFailed": "CSV എക്സ്പോർട്ട് പരാജയപ്പെട്ടു",
      "tryAgainOrSupport": "ദയവായി വീണ്ടും ശ്രമിക്കുക അല്ലെങ്കിൽ പിന്തുണയുമായി ബന്ധപ്പെടുക."
    },
    "filters": {
      "customizeView": "നിങ്ങളുടെ റിപ്പോർട്ട് കാഴ്ച ഇഷ്ടാനുസൃതമാക്കുക",
      "apply": "പ്രയോഗിക്കുക",
      "selectWard": "വാർഡ് തിരഞ്ഞെടുക്കുക",
      "loadingWards": "വാർഡുകൾ ലോഡ് ചെയ്യുന്നു...",
      "allWards": "എല്ലാ വാർഡുകളും",
      "selectType": "തരം തിരഞ്ഞെടുക്കുക",
      "allTypes": "എല്ലാ തരങ്ങളും",
      "loadingTypes": "തരങ്ങൾ ലോഡ് ചെയ്യുന്നു...",
      "noTypesAvailable": "തരങ്ങൾ ലഭ്യമല്ല",
      "selectStatus": "സ്ഥിതി തിരഞ്ഞെടുക്കുക",
      "allStatus": "എല്ലാ സ്ഥിതികളും",
      "activeFilters": "സജീവ ഫിൽറ്ററുകൾ",
      "noFiltersApplied": "ഫിൽറ്ററുകൾ പ്രയോഗിച്ചിട്ടില്ല",
      "reset": "പുനഃസജ്ജമാക്കുക"
    },
    "kpi": {
      "totalComplaints": "മൊത്തം പരാതികൾ",
      "avg": "ശരാശരി",
      "days": "ദിവസങ്ങൾ",
      "hours": "മണിക്കൂറുകൾ",
      "daysShort": "ദി",
      "fromLastPeriod": "കഴിഞ്ഞ കാലയളവിൽ നിന്ന്",
      "noPreviousData": "മുൻ ഡാറ്റയില്ല"
    },
    "tabs": {
      "wardAnalysis": "വാർഡ് വിശകലനം",
      "categories": "വിഭാഗങ്ങൾ"
    },
    "charts": {
      "complaintsTrend": "പരാതി പ്രവണത",
      "categoryDistribution": "വിഭാഗ വിതരണം",
      "detailedTrendsAnalysis": "വിശദമായ പ്രവണത വിശകലനം",
      "resolutionTimeDistribution": "പരിഹാര സമയ വിതരണം",
      "wardPerformanceComparison": "വാർഡ് പ്രകടന താരതമ്യം",
      "categoryAnalysis": "വിഭാഗ വിശകലനം",
      "noTrendData": "പ്രവണത ഡാറ്റ ലഭ്യമല്ല",
      "noCategoryData": "വിഭാഗ ഡാറ്റ ലഭ്യമല്ല",
      "noCategoryMetrics": "വിഭാഗ മെട്രിക്സ് ലഭ്യമല്ല",
      "noWardComparisonData": "വാർഡ് താരതമ്യ ഡാറ്റ ലഭ്യമല്ല",
      "loadingChart": "ചാർട്ട് ലോഡ് ചെയ്യുന്നു...",
      "chartTypeNotSupported": "ചാർട്ട് തരം പിന്തുണയ്ക്കുന്നില്ല",
      "errorLoadingChart": "ചാർട്ട് ലോഡ് ചെയ്യുന്നതിൽ പിശക്",
      "resolvedComplaints": "പരിഹരിച്ച പരാതികൾ",
      "avgResolutionTime": "ശരാശരി പരിഹാര സമയം",
      "category": "വിഭാഗം"
    },
    "heatmap": {
      "complaintsWardsTitle": "പരാതികൾ × വാർഡുകൾ ഹീറ്റ്മാപ്",
      "complaintsSubzonesTitle": "പരാതികൾ × ഉപമേഖലകൾ ഹീറ്റ്മാപ്",
      "complaintsWardsDesc": "എല്ലാ വാർഡുകളിലും തരം അനുസരിച്ച് പരാതികളുടെ വിതരണം",
      "complaintsSubzonesDesc": "ഉപമേഖലകളിൽ തരം അനുസരിച്ച് പരാതികളുടെ വിതരണം",
      "subzone": "ഉപമേഖല",
      "updating": "ഹീറ്റ്മാപ് അപ്ഡേറ്റ് ചെയ്യുന്നു..."
    },
    "modal": {
      "generatingReport": "റിപ്പോർട്ട് ജനറേറ്റ് ചെയ്യുന്നു",
      "processingData": "നിങ്ങളുടെ ഡാറ്റ പ്രോസസ്സ് ചെയ്യുന്നു...",
      "analyzing": "വിശകലനം ചെയ്യുന്നു",
      "estimatedTime": "കണക്കാക്കിയ സമയം",
      "remaining": "ബാക്കി",
      "finalizingReport": "റിപ്പോർട്ട് അന്തിമമാക്കുന്നു...",
      "reportScope": "റിപ്പോർട്ട് സ്കോപ്പ്",
      "period": "കാലയളവ്"
    },
    "loading": {
      "chartLibraries": "ചാർട്ട് ലൈബ്രറികൾ ലോഡ് ചെയ്യുന്നു..."
    },
    "timePeriod": {
      "pastWeek": "കഴിഞ്ഞ ആഴ്ച",
      "pastMonth": "കഴിഞ്ഞ മാസം",
      "past3Months": "കഴിഞ്ഞ 3 മാസം"
    },
    "errors": {
      "featureLoadingError": "ഫീച്ചർ ലോഡിംഗ് പിശക്",
      "retryLoadingFeatures": "ഫീച്ചറുകൾ ലോഡ് ചെയ്യാൻ വീണ്ടും ശ്രമിക്കുക",
      "libraryLoadError": "ആവശ്യമായ ലൈബ്രറികൾ ലോഡ് ചെയ്യുന്നതിൽ പരാജയപ്പെട്ടു. ചില ഫീച്ചറുകൾ പ്രവർത്തിച്ചേക്കില്ല.",
      "reportGenerationFailed": "റിപ്പോർട്ട് ജനറേഷൻ പരാജയപ്പെട്ടു",
      "reportError": "റിപ്പോർട്ട് ജനറേറ്റ് ചെയ്യുന്നതിൽ പരാജയപ്പെട്ടു"
    },
    "print": "പ്രിന്റ് ചെയ്യുക",
    "chart": "ചാർട്ട്",
    "table": "പട്ടിക",
    "summary": "സംഗ്രഹം",
    "details": "വിശദാംശങ്ങൾ"
  },
  "admin": {
    "config": {
      "title": "സിസ്റ്റം കോൺഫിഗറേഷൻ",
      "subtitle": "സിസ്റ്റം ക്രമീകരണങ്ങൾ, വാർഡുകൾ, പരാതി തരങ്ങൾ, മറ്റ് കോൺഫിഗറേഷനുകൾ എന്നിവ മാനേജ് ചെയ്യുക",
      "systemSettings": "സിസ്റ്റം ക്രമീകരണങ്ങൾ",
      "wardsBoundaries": "വാർഡുകളും അതിർത്തികളും",
      "complaintTypes": "പരാതി തരങ്ങൾ",
      "userManagement": "ഉപയോക്തൃ മാനേജ്മെന്റ്",
      "userManagementDescription": "ഉപയോക്തൃ മാനേജ്മെന്റ് ഇന്റർഫേസ് ഇവിടെ നടപ്പിലാക്കും"
    },
    "systemSettings": {
      "title": "സിസ്റ്റം കോൺഫിഗറേഷൻ",
      "subtitle": "എനേബിൾ/ഡിസേബിൾ കൺട്രോളുകളോടെ എല്ലാ സിസ്റ്റം ക്രമീകരണങ്ങളും മാനേജ് ചെയ്യുക",
      "searchPlaceholder": "ക്രമീകരണങ്ങൾ തിരയുക...",
      "resetChanges": "മാറ്റങ്ങൾ പുനഃസജ്ജമാക്കുക",
      "saveChanges": "മാറ്റങ്ങൾ സേവ് ചെയ്യുക",
      "refresh": "പുതുക്കുക",
      "loadingSettings": "സിസ്റ്റം ക്രമീകരണങ്ങൾ ലോഡ് ചെയ്യുന്നു...",
      "errorLoadingSettings": "ക്രമീകരണങ്ങൾ ലോഡ് ചെയ്യുന്നതിൽ പിശക്",
      "failedToLoadConfig": "സിസ്റ്റം കോൺഫിഗറേഷൻ ലോഡ് ചെയ്യുന്നതിൽ പരാജയപ്പെട്ടു",
      "tryAgain": "വീണ്ടും ശ്രമിക്കുക",
      "noChanges": "മാറ്റങ്ങളൊന്നുമില്ല",
      "noChangesToSave": "സേവ് ചെയ്യാൻ മാറ്റങ്ങളൊന്നുമില്ല",
      "settingsSaved": "ക്രമീകരണങ്ങൾ സേവ് ചെയ്തു",
      "updatedSettings": "{{count}} ക്രമീകരണങ്ങൾ വിജയകരമായി അപ്ഡേറ്റ് ചെയ്തു",
      "saveFailed": "സേവ് പരാജയപ്പെട്ടു",
      "failedToSaveSettings": "ക്രമീകരണങ്ങൾ സേവ് ചെയ്യുന്നതിൽ പരാജയപ്പെട്ടു",
      "noSettingsFound": "ക്രമീകരണങ്ങളൊന്നും കണ്ടെത്തിയില്ല",
      "adjustSearchTerms": "നിങ്ങളുടെ തിരയൽ പദങ്ങൾ ക്രമീകരിക്കാൻ ശ്രമിക്കുക",
      "settings": "ക്രമീകരണങ്ങൾ",
      "active": "സജീവം",
      "inactive": "നിഷ്ക്രിയം",
      "value": "മൂല്യം",
      "key": "കീ",
      "type": "തരം",
      "enabled": "പ്രവർത്തനക്ഷമം",
      "disabled": "പ്രവർത്തനരഹിതം",
      "enterValidJson": "സാധുവായ JSON നൽകുക",
      "enterValue": "{{type}} മൂല്യം നൽകുക",
      "small": "ചെറുത്",
      "medium": "ഇടത്തരം",
      "large": "വലുത്",
      "sections": {
        "applicationSettings": "ആപ്ലിക്കേഷൻ ക്രമീകരണങ്ങൾ",
        "applicationSettingsDesc": "ആപ്ലിക്കേഷൻ ബ്രാൻഡിംഗും പൊതു ക്രമീകരണങ്ങളും",
        "complaintManagement": "പരാതി മാനേജ്മെന്റ്",
        "complaintManagementDesc": "പരാതി സമർപ്പണവും മാനേജ്മെന്റ് ക്രമീകരണങ്ങളും",
        "geographicSettings": "ഭൂമിശാസ്ത്രപരവും സ്ഥാന ക്രമീകരണങ്ങളും",
        "geographicSettingsDesc": "ഭൂമിശാസ്ത്രപരവും സ്ഥാന-അടിസ്ഥാന കോൺഫിഗറേഷനും",
        "contactInformation": "ബന്ധപ്പെടാനുള്ള വിവരങ്ങൾ",
        "contactInformationDesc": "ബന്ധപ്പെടാനുള്ള വിശദാംശങ്ങളും ഓഫീസ് വിവരങ്ങളും",
        "systemBehavior": "സിസ്റ്റം പെരുമാറ്റം",
        "systemBehaviorDesc": "പ്രധാന സിസ്റ്റം പ്രവർത്തനക്ഷമതയും പെരുമാറ്റവും",
        "notificationCommunication": "അറിയിപ്പും ആശയവിനിമയവും",
        "notificationCommunicationDesc": "അറിയിപ്പ് ക്രമീകരണങ്ങളും ആശയവിനിമയ മുൻഗണനകളും",
        "systemDataStructures": "സിസ്റ്റം ഡാറ്റ ഘടനകൾ",
        "systemDataStructuresDesc": "സിസ്റ്റം ഡാറ്റ ഘടനകളും കോൺഫിഗറേഷനുകളും"
      },
      "labels": {
        "appName": "ആപ്ലിക്കേഷൻ പേര്",
        "logoUrl": "ലോഗോ URL",
        "logoSize": "ലോഗോ വലുപ്പം",
        "adminEmail": "അഡ്മിനിസ്ട്രേറ്റർ ഇമെയിൽ",
        "complaintIdPrefix": "പരാതി ID പ്രിഫിക്സ്",
        "idStartNumber": "ID ആരംഭ നമ്പർ",
        "idNumberLength": "ID നമ്പർ നീളം",
        "maxPhotoSize": "പരമാവധി ഫോട്ടോ വലുപ്പം (MB)",
        "maxPhotoCount": "പരമാവധി ഫോട്ടോ എണ്ണം",
        "dailyComplaintLimit": "ദൈനംദിന പരാതി പരിധി",
        "enableDailyLimit": "ദൈനംദിന പരിധി പ്രവർത്തനക്ഷമമാക്കുക",
        "allowGuestComplaints": "അതിഥി പരാതികൾ അനുവദിക്കുക",
        "defaultSlaHours": "ഡിഫോൾട്ട് SLA മണിക്കൂറുകൾ",
        "searchPlaceContext": "സ്ഥലം തിരയൽ സന്ദർഭം",
        "countryCodes": "രാജ്യ കോഡുകൾ (ISO2)",
        "defaultLatitude": "ഡിഫോൾട്ട് അക്ഷാംശം",
        "defaultLongitude": "ഡിഫോൾട്ട് രേഖാംശം",
        "boundingBoxNorth": "ബൗണ്ടിംഗ് ബോക്സ് വടക്ക്",
        "boundingBoxSouth": "ബൗണ്ടിംഗ് ബോക്സ് തെക്ക്",
        "boundingBoxEast": "ബൗണ്ടിംഗ് ബോക്സ് കിഴക്ക്",
        "boundingBoxWest": "ബൗണ്ടിംഗ് ബോക്സ് പടിഞ്ഞാറ്",
        "serviceAreaBoundary": "സേവന മേഖല അതിർത്തി (GeoJSON)",
        "enableLocationValidation": "സ്ഥാന സാധൂകരണം പ്രവർത്തനക്ഷമമാക്കുക",
        "helplineNumber": "ഹെൽപ്പ്ലൈൻ നമ്പർ",
        "supportEmail": "സപ്പോർട്ട് ഇമെയിൽ",
        "officeHours": "ഓഫീസ് സമയം",
        "officeAddress": "ഓഫീസ് വിലാസം",
        "autoAssignComplaints": "പരാതികൾ സ്വയമേവ അസൈൻ ചെയ്യുക",
        "allowCitizenRegistration": "പൗര രജിസ്ട്രേഷൻ അനുവദിക്കുക",
        "otpExpiryMinutes": "OTP കാലാവധി മിനിറ്റുകൾ",
        "maxFileSize": "പരമാവധി ഫയൽ വലുപ്പം (MB)",
        "notificationConfig": "അറിയിപ്പ് കോൺഫിഗറേഷൻ (JSON)",
        "complaintPriorities": "പരാതി മുൻഗണനകൾ (JSON)",
        "complaintStatuses": "പരാതി നിലകൾ (JSON)"
      }
    },
    "users": {
      "title": "User Management",
      "subtitle": "Manage all users in the system",
      "roles": {
        "citizen": "Citizen",
        "wardOfficer": "Ward Officer",
        "maintenanceTeam": "Maintenance Team",
        "administrator": "Administrator"
      },
      "stats": {
        "totalUsers": "Total Users",
        "activeUsers": "Active Users",
        "citizens": "Citizens",
        "wardOfficers": "Ward Officers",
        "maintenance": "Maintenance"
      },
      "filters": {
        "searchPlaceholder": "Search users...",
        "rolePlaceholder": "Filter by role",
        "statusPlaceholder": "Filter by status",
        "allRoles": "All Roles",
        "allStatus": "All Status",
        "reset": "Reset Filters"
      },
      "table": {
        "title": "Users ({{count}})",
        "loading": "Loading users...",
        "noWard": "No ward assigned",
        "columns": {
          "name": "User",
          "role": "Role",
          "ward": "Ward",
          "status": "Status",
          "activity": "Complaints",
          "actions": "Actions"
        }
      },
      "status": {
        "active": "Active",
        "inactive": "Inactive"
      },
      "counts": {
        "submitted": "Submitted: {{count}}",
        "assigned": "Assigned: {{count}}"
      },
      "pagination": {
        "showing": "Showing {{start}} to {{end}} of {{total}} entries"
      },
      "actions": {
        "exportUsers": "Export Users",
        "addUser": "Add New User",
        "editUser": "Edit user",
        "deactivateUser": "Deactivate user",
        "activateUser": "Activate user",
        "createUser": "Create User",
        "updateUser": "Update User",
        "creating": "Creating...",
        "updating": "Updating..."
      },
      "dialogs": {
        "add": {
          "title": "Add New User",
          "description": "Create a new user account in the system. All fields marked with * are required."
        },
        "edit": {
          "title": "Edit User",
          "description": "Update user information. Changes will be applied immediately."
        }
      },
      "fields": {
        "fullName": "Full Name",
        "fullNamePlaceholder": "Enter full name",
        "email": "Email",
        "emailPlaceholder": "Enter email address",
        "phoneNumber": "Phone Number",
        "phonePlaceholder": "Enter phone number",
        "role": "Role",
        "rolePlaceholder": "Select role",
        "ward": "Ward",
        "wardPlaceholder": "Select ward (optional)",
        "noWardOption": "No ward assigned",
        "department": "Department",
        "departmentPlaceholder": "Enter department"
      },
      "toasts": {
        "activated": "User activated successfully",
        "activateFailed": "Failed to activate user",
        "deactivated": "User deactivated successfully",
        "deactivateFailed": "Failed to deactivate user",
        "createSuccess": "User created successfully",
        "updateSuccess": "User updated successfully",
        "unexpectedError": "Unexpected error",
        "exportFailed": "Export failed",
        "exportFailedDescription": "Could not export users"
      },
      "validation": {
        "fullNameMin": "Full name must be at least 3 characters.",
        "emailRequired": "Email is required.",
        "emailInvalid": "Please enter a valid email address.",
        "roleRequired": "Role is required.",
        "departmentRequired": "Department is required for maintenance team users.",
        "title": "Validation errors",
        "message": "Please fix the highlighted fields before submitting."
      },
      "errors": {
        "loadTitle": "Error Loading Data",
        "loadMessage": "Failed to load user data. Please try again."
      }
    }
  },
  "index": {
    "title": "പരാതി മാനേജ്മെന്റ് പോർട്ടൽ",
    "subtitle": "പരാതി മാനേജ്മെന്റ് സിസ്റ്റത്തിലേക്ക് സ്വാഗതം. പൗര പ്രശ്നങ്ങൾ സമർപ്പിക്കുക, പുരോഗതി ട്രാക്ക് ചെയ്യുക, മികച്ച നഗരം നിർമ്മിക്കാൻ സഹായിക്കുക.",
    "heroTitle": "{{appName}} പോർട്ടൽ",
    "trackYourComplaint": "നിങ്ങളുടെ പരാതി ട്രാക്ക് ചെയ്യുക",
    "complaintIdPlaceholder": "നിങ്ങളുടെ പരാതി ഐഡി നൽകുക (ഉദാ., {{example}})",
    "verifyAndTrack": "സ്ഥിരീകരിച്ച് ട്രാക്ക് ചെയ്യുക",
    "sending": "അയയ്ക്കുന്നു...",
    "keyFeatures": "പ്രധാന സവിശേഷതകൾ",
    "realTimeTracking": "റിയൽ-ടൈം ട്രാക്കിംഗ്",
    "realTimeTrackingDesc": "തൽക്ഷണ അപ്ഡേറ്റുകളോടെ പരാതിയുടെ പുരോഗതി റിയൽ ടൈമിൽ നിരീക്ഷിക്കുക",
    "quickRegistration": "വേഗത്തിലുള്ള പരാതി രജിസ്ട്രേഷൻ",
    "quickRegistrationDesc": "തരം, ഫോട്ടോ, സ്ഥാനം എന്നിവയോടെ ഒരു മിനിറ്റിനുള്ളിൽ പ്രശ്നങ്ങൾ ലോഗ് ചെയ്യുക",
    "emailAlerts": "ഇമെയിൽ അലേർട്ടുകൾ",
    "emailAlertsDesc": "ഓരോ ഘട്ടത്തിലും അറിയിപ്പ് ലഭിക്കുക — രജിസ്ട്രേഷൻ മുതൽ പരിഹാരം വരെ",
    "multilingualSupport": "ബഹുഭാഷാ പിന്തുണ",
    "multilingualSupportDesc": "ഇംഗ്ലീഷ്, മലയാളം, ഹിന്ദി എന്നിവയിൽ ലഭ്യം",
    "needHelpContactUs": "സഹായം വേണോ? ഞങ്ങളെ ബന്ധപ്പെടുക",
    "helpline": "ഹെൽപ്പ്‌ലൈൻ",
    "emailSupport": "ഇമെയിൽ പിന്തുണ",
    "officeHours": "ഓഫീസ് സമയം",
    "officeLocation": "ഓഫീസ് സ്ഥാനം",
    "complaintNotFound": "പരാതി കണ്ടെത്തിയില്ല. ദയവായി നിങ്ങളുടെ പരാതി ഐഡി പരിശോധിക്കുക."
  },
  "forms": {
    "contactInformation": "ബന്ധപ്പെടാനുള്ള വിവരങ്ങൾ",
    "problemDetails": "പ്രശ്ന വിശദാംശങ്ങൾ",
    "locationDetails": "സ്ഥാന വിശദാംശങ്ങൾ",
    "complaintDescription": "പരാതി വിവരണം",
    "optionalUploads": "ഓപ്ഷണൽ അപ്‌ലോഡുകൾ",
    "captchaVerification": "കാപ്ച്ച സ്ഥിരീകരണം",
    "enterCaptcha": "മുകളിൽ കാണിച്ചിരിക്കുന്ന കോഡ് നൽകുക",
    "resetForm": "ഫോം റീസെറ്റ് ചെയ്യുക",
    "submitComplaint": "പരാതി സമർപ്പിക്കുക",
    "complaintSubmitted": "പരാതി വിജയകരമായി സമർപ്പിച്ചു!",
    "complaintSubmissionError": "പരാതി സമർപ്പിക്കുന്നതിൽ പരാജയപ്പെട്ടു",
    "fileUploadError": "ഫയൽ അപ്‌ലോഡ് പരാജയപ്പെട്ടു",
    "invalidCaptcha": "അസാധുവായ കാപ്ച്ച കോഡ്",
    "requiredField": "ഈ ഫീൽഡ് ആവശ്യമാണ്",
    "invalidEmail": "അസാധുവായ ഇമെയിൽ വിലാസം",
    "invalidPhone": "അസാധുവായ ഫോൺ നമ്പർ",
    "minCharacters": "കുറഞ്ഞത് 3 അക്ഷരങ്ങൾ ആവശ്യമാണ്",
    "enterComplete6DigitCode": "ദയവായി പൂർണ്ണമായ 6-അക്ക കോഡ് നൽകുക",
    "verifyYourIdentity": "നിങ്ങളുടെ ഐഡന്റിറ്റി സ്ഥിരീകരിക്കുക",
    "enter6DigitCodeLogin": "ലോഗിൻ ചെയ്യാൻ നിങ്ങളുടെ ഇമെയിലിലേക്ക് അയച്ച 6-അക്ക കോഡ് നൽകുക",
    "verifyAndLogin": "സ്ഥിരീകരിച്ച് ലോഗിൻ ചെയ്യുക",
    "completeRegistration": "രജിസ്ട്രേഷൻ പൂർത്തിയാക്കുക",
    "enter6DigitCodeActivate": "നിങ്ങളുടെ അക്കൗണ്ട് സജീവമാക്കാൻ നിങ്ങളുടെ ഇമെയിലിലേക്ക് അയച്ച 6-അക്ക കോഡ് നൽകുക",
    "verifyAndCompleteRegistration": "സ്ഥിരീകരിച്ച് രജിസ്ട്രേഷൻ പൂർത്തിയാക്കുക",
    "verifyYourComplaint": "നിങ്ങളുടെ പരാതി സ്ഥിരീകരിക്കുക",
    "enter6DigitCodeComplaint": "നിങ്ങളുടെ പരാതി സമർപ്പണം പൂർത്തിയാക്കാൻ നിങ്ങളുടെ ഇമെയിലിലേക്ക് അയച്ച 6-അക്ക കോഡ് നൽകുക",
    "verifyAndActivateComplaint": "സ്ഥിരീകരിച്ച് പരാതി സജീവമാക്കുക",
    "verifyYourAccess": "നിങ്ങളുടെ ആക്സസ് സ്ഥിരീകരിക്കുക",
    "enter6DigitCodeAccess": "ഈ പരാതി ആക്സസ് ചെയ്യാൻ നിങ്ങളുടെ ഇമെയിലിലേക്ക് അയച്ച 6-അക്ക കോഡ് നൽകുക",
    "verifyAndContinue": "സ്ഥിരീകരിച്ച് തുടരുക",
    "verifyOtp": "OTP സ്ഥിരീകരിക്കുക",
    "enter6DigitCodeEmail": "നിങ്ങളുടെ ഇമെയിലിലേക്ക് അയച്ച 6-അക്ക കോഡ് നൽകുക",
    "enter6DigitCode": "6-അക്ക കോഡ് നൽകുക",
    "verifying": "സ്ഥിരീകരിക്കുന്നു...",
    "expiresIn": "കാലാവധി",
    "sending": "അയയ്ക്കുന്നു...",
    "resendOtp": "OTP വീണ്ടും അയയ്ക്കുക",
    "verificationCodeSentSecurity": "നിങ്ങളുടെ പരാതി വിശദാംശങ്ങളുടെ സുരക്ഷ ഉറപ്പാക്കാൻ ഞങ്ങൾ നിങ്ങളുടെ ഇമെയിൽ വിലാസത്തിലേക്ക് ഒരു സ്ഥിരീകരണ കോഡ് അയച്ചിട്ടുണ്ട്.",
    "codeSentTo": "കോഡ് അയച്ചത്",
    "checkInboxSpam": "നിങ്ങളുടെ ഇൻബോക്സും സ്പാം ഫോൾഡറും പരിശോധിക്കുക",
    "enter6DigitVerificationCode": "6-അക്ക സ്ഥിരീകരണ കോഡ് നൽകുക",
    "enter6DigitCodeFromEmail": "നിങ്ങളുടെ ഇമെയിലിൽ നിന്ന് 6-അക്ക കോഡ് നൽകുക",
    "codeExpiresIn": "കോഡിന്റെ കാലാവധി",
    "codeExpired": "കോഡിന്റെ കാലാവധി കഴിഞ്ഞു",
    "codeEnteredSuccessfully": "കോഡ് വിജയകരമായി നൽകി. തുടരാൻ സ്ഥിരീകരിക്കുക ക്ലിക്ക് ചെയ്യുക.",
    "verifyCode": "കോഡ് സ്ഥിരീകരിക്കുക",
    "resend": "വീണ്ടും അയയ്ക്കുക",
    "didntReceiveCode": "കോഡ് ലഭിച്ചില്ലേ?",
    "clickToResend": "വീണ്ടും അയയ്ക്കാൻ ക്ലിക്ക് ചെയ്യുക",
    "wait": "കാത്തിരിക്കുക",
    "toResend": "വീണ്ടും അയയ്ക്കാൻ",
    "securityNote": "സുരക്ഷാ കുറിപ്പ്",
    "neverShareCode": "ഈ കോഡ് ആരുമായും പങ്കിടരുത്. ഞങ്ങളുടെ ടീം നിങ്ങളുടെ സ്ഥിരീകരണ കോഡ് ചോദിക്കില്ല.",
    "complaintSubmittedSuccessfully": "പരാതി വിജയകരമായി സമർപ്പിച്ചു!",
    "complaintRegisteredWithId": "നിങ്ങളുടെ പരാതി ഐഡി: {{complaintId}} ഉപയോഗിച്ച് രജിസ്റ്റർ ചെയ്തിട്ടുണ്ട്. നിങ്ങൾക്ക് നിങ്ങളുടെ ഡാഷ്ബോർഡിൽ നിന്ന് അതിന്റെ പുരോഗതി ട്രാക്ക് ചെയ്യാം.",
    "verificationCodeSent": "സ്ഥിരീകരണ കോഡ് അയച്ചു",
    "verificationCodeSentToEmail": "{{email}} ലേക്ക് ഒരു സ്ഥിരീകരണ കോഡ് അയച്ചിട്ടുണ്ട്. ദയവായി നിങ്ങളുടെ ഇമെയിൽ പരിശോധിച്ച് താഴെ കോഡ് നൽകുക.",
    "submissionFailed": "സമർപ്പണം പരാജയപ്പെട്ടു",
    "failedToSubmitComplaint": "പരാതി സമർപ്പിക്കുന്നതിൽ പരാജയപ്പെട്ടു. ദയവായി വീണ്ടും ശ്രമിക്കുക.",
    "invalidCode": "അസാധുവായ കോഡ്",
    "enterValid6DigitCode": "ദയവായി സാധുവായ 6-അക്ക സ്ഥിരീകരണ കോഡ് നൽകുക.",
    "success": "വിജയം!",
    "complaintVerifiedAccountCreated": "നിങ്ങളുടെ പരാതി സ്ഥിരീകരിക്കപ്പെട്ടു, നിങ്ങളുടെ പൗര അക്കൗണ്ട് വിജയകരമായി സൃഷ്ടിക്കപ്പെട്ടു!",
    "complaintVerifiedLoggedIn": "നിങ്ങളുടെ പരാതി സ്ഥിരീകരിക്കപ്പെട്ടു, നിങ്ങൾ വിജയകരമായി ലോഗിൻ ചെയ്തിരിക്കുന്നു!",
    "verificationFailed": "സ്ഥിരീകരണം പരാജയപ്പെട്ടു",
    "invalidVerificationCode": "അസാധുവായ സ്ഥിരീകരണ കോഡ്. ദയവായി വീണ്ടും ശ്രമിക്കുക.",
    "invalidFileType": "അസാധുവായ ഫയൽ തരം",
    "onlyJpgPngAllowed": "JPG, PNG ചിത്രങ്ങൾ മാത്രമേ അനുവദിക്കൂ",
    "areaMinCharacters": "പ്രദേശം കുറഞ്ഞത് 3 അക്ഷരങ്ങൾ ആയിരിക്കണം",
    "descriptionMinCharacters": "വിവരണം കുറഞ്ഞത് 10 അക്ഷരങ്ങൾ ആയിരിക്കണം",
    "completeCaptchaVerification": "ദയവായി കാപ്ച്ച സ്ഥിരീകരണം പൂർത്തിയാക്കുക",
    "enterYourFullName": "നിങ്ങളുടെ പൂർണ്ണ നാമം നൽകുക",
    "enterYourMobileNumber": "നിങ്ങളുടെ മൊബൈൽ നമ്പർ നൽകുക",
    "enterYourEmailAddress": "നിങ്ങളുടെ ഇമെയിൽ വിലാസം നൽകുക",
    "selectComplaintType": "പരാതി തരം തിരഞ്ഞെടുക്കുക",
    "selectYourWard": "നിങ്ങളുടെ വാർഡ് തിരഞ്ഞെടുക്കുക",
    "emailVerification": "ഇമെയിൽ സ്ഥിരീകരണം",
    "enterVerificationCode": "സ്ഥിരീകരണ കോഡ് നൽകുക",
    "verifyAndSubmit": "സ്ഥിരീകരിച്ച് സമർപ്പിക്കുക",
    "sendingCode": "കോഡ് അയയ്ക്കുന്നു...",
    "submitAndSendVerification": "സമർപ്പിച്ച് സ്ഥിരീകരണം അയയ്ക്കുക",
    "errorLoadingWards": "വാർഡുകൾ ലോഡ് ചെയ്യുന്നതിൽ പിശക്",
    "loadingWards": "വാർഡുകൾ ലോഡ് ചെയ്യുന്നു...",
    "loadingCaptcha": "കാപ്ച്ച ലോഡ് ചെയ്യുന്നു...",
    "errorLoadingCaptcha": "കാപ്ച്ച ലോഡ് ചെയ്യുന്നതിൽ പിശക്",
    "clickRefreshCaptcha": "കാപ്ച്ച ലോഡ് ചെയ്യാൻ റിഫ്രഷ് ക്ലിക്ക് ചെയ്യുക",
    "verificationCodeResent": "സ്ഥിരീകരണ കോഡ് വീണ്ടും അയച്ചു",
    "newVerificationCodeSent": "നിങ്ങളുടെ ഇമെയിലിലേക്ക് ഒരു പുതിയ സ്ഥിരീകരണ കോഡ് അയച്ചിട്ടുണ്ട്.",
    "failedToResend": "വീണ്ടും അയയ്ക്കുന്നതിൽ പരാജയപ്പെട്ടു",
    "failedToResendVerificationCode": "സ്ഥിരീകരണ കോഡ് വീണ്ടും അയയ്ക്കുന്നതിൽ പരാജയപ്പെട്ടു."
  },
  "loading": {
    "default": "ലോഡ് ചെയ്യുന്നു...",
    "dashboard": "ഡാഷ്ബോർഡ് ഡാറ്റ ലോഡ് ചെയ്യുന്നു...",
    "complaints": "പരാതികൾ ലോഡ് ചെയ്യുന്നു...",
    "saving": "സംരക്ഷിക്കുന്നു...",
    "submitting": "സമർപ്പിക്കുന്നു...",
    "refreshing": "പുതുക്കുന്നു..."
  },
  "errors": {
    "loadingFailed": "ഡാറ്റ ലോഡ് ചെയ്യുന്നതിൽ പരാജയപ്പെട്ടു",
    "networkError": "നെറ്റ്‌വർക്ക് കണക്ഷൻ പിശക്",
    "unauthorized": "ഈ പ്രവർത്തനം നടത്താൻ നിങ്ങൾക്ക് അധികാരമില്ല",
    "sessionExpired": "നിങ്ങളുടെ സെഷൻ കാലഹരണപ്പെട്ടു. ദയവായി വീണ്ടും ലോഗിൻ ചെയ്യുക",
    "validationFailed": "ദയവായി നിങ്ങളുടെ ഇൻപുട്ട് പരിശോധിച്ച് വീണ്ടും ശ്രമിക്കുക",
    "somethingWentWrong": "എന്തോ തെറ്റ് സംഭവിച്ചു"
  },
  "messages": {
    "complaintRegistered": "പരാതി വിജയകരമായി രജിസ്റ്റർ ചെയ്തു",
    "complaintUpdated": "പരാതി വിജയകരമായി അപ്ഡേറ്റ് ചെയ്തു",
    "complaintResolved": "പരാതി വിജയകരമായി പരിഹരിച്ചു",
    "profileUpdated": "പ്രൊഫൈൽ വിജയകരമായി അപ്ഡേറ്റ് ചെയ്തു",
    "passwordChanged": "പാസ്വേഡ് വിജയകരമായി മാറ്റി",
    "loginSuccessful": "ലോഗിൻ വിജയകരം",
    "logoutSuccessful": "ലോഗൗട്ട് വിജയകരം",
    "registrationSuccessful": "രജിസ്ട്രേഷൻ വിജയകരം",
    "emailSent": "ഇമെയിൽ വിജയകരമായി അയച്ചു",
    "fileUploaded": "ഫയൽ വിജയകരമായി അപ്‌ലോഡ് ചെയ്തു",
    "feedbackSubmitted": "ഫീഡ്ബാക്ക് വിജയകരമായി സമർപ്പിച്ചു",
    "assignmentCompleted": "അസൈൻമെന്റ് വിജയകരമായി പൂർത്തിയായി",
    "statusUpdated": "സ്ഥിതി വിജയകരമായി അപ്ഡേറ്റ് ചെയ്തു",
    "errorOccurred": "ഒരു പിശക് സംഭവിച്ചു",
    "networkError": "നെറ്റ്‌വർക്ക് പിശക്",
    "unauthorizedAccess": "അനധികൃത ആക്സസ്",
    "sessionExpired": "സെഷൻ കാലഹരണപ്പെട്ടു",
    "validationError": "സാധൂകരണം പിശക്",
    "serverError": "സെർവർ പിശക് സംഭവിച്ചു",
    "welcomeBack": "തിരിച്ചുവരവിന് സ്വാഗതം!",
    "chooseLoginMethod": "നിങ്ങളുടെ ഇഷ്ടപ്പെട്ട ലോഗിൻ രീതി തിരഞ്ഞെടുക്കുക",
    "passwordSetupSent": "പാസ്വേഡ് സെറ്റപ്പ് നിർദ്ദേശങ്ങൾ {{email}} ലേക്ക് അയച്ചു. ദയവായി നിങ്ങളുടെ ഇമെയിൽ പരിശോധിച്ച് നിർദ്ദേശങ്ങൾ പാലിക്കുക.",
    "demoCredentials": "ഡെമോ ക്രെഡൻഷ്യലുകൾ",
    "testingPurposes": "പരീക്ഷണ ആവശ്യങ്ങൾക്ക് മാത്രം",
    "eGovernancePortal": "ഇ-ഗവേണൻസ് പോർട്ടൽ",
    "otpCodeSent": "ഞങ്ങൾ നിങ്ങളുടെ ഇമെയിൽ വിലാസത്തിലേക്ക് 6-അക്ക കോഡ് അയയ്ക്കും",
    "noAccount": "അക്കൗണ്ട് ഇല്ലേ?",
    "registerHere": "ഇവിടെ രജിസ്റ്റർ ചെയ്യുക",
    "backToHome": "ഹോമിലേക്ക് തിരിച്ചുപോകുക"
  },
  "maintenance": {
    "dashboard": {
      "title": "പരിചരണ ഡാഷ്ബോർഡ്",
      "subtitle": "നിങ്ങളുടെ അസൈൻ ചെയ്ത ജോലികൾ കൈകാര്യം ചെയ്യുകയും ഫീൽഡ് വർക്ക് പുരോഗതി ട്രാക്ക് ചെയ്യുകയും ചെയ്യുക",
      "loadingTasks": "നിങ്ങളുടെ അസൈൻ ചെയ്ത ജോലികൾ ലോഡ് ചെയ്യുന്നു...",
      "error": "ഡാഷ്ബോർഡ് പിശക്",
      "errorMessage": "നിങ്ങളുടെ ജോലികൾ ലോഡ് ചെയ്യുന്നതിൽ പരാജയപ്പെട്ടു. ദയവായി വീണ്ടും ശ്രമിക്കുക.",
      "fieldWork": "ഫീൽഡ് വർക്ക്",
      "startTasks": "നിങ്ങളുടെ ജോലികൾ ആരംഭിക്കുക",
      "updateData": "ഡാറ്റ അപ്ഡേറ്റ് ചെയ്യുക",
      "debugInfo": "ഡിബഗ് വിവരം (ഡെവ് മോഡ്)",
      "totalComplaintsFetched": "മൊത്തം പരാതികൾ ലഭിച്ചു",
      "userId": "ഉപയോക്തൃ ഐഡി",
      "userRole": "ഉപയോക്തൃ റോൾ",
      "myTasksCount": "എന്റെ ജോലികളുടെ എണ്ണം",
      "sampleTask": "സാമ്പിൾ ജോലി",
      "totalTasks": "മൊത്തം ജോലികൾ",
      "assignedToYou": "നിങ്ങൾക്ക് അസൈൻ ചെയ്തത്",
      "todaysTasks": "ഇന്നത്തെ ജോലികൾ",
      "scheduledForToday": "ഇന്നത്തേക്ക് ഷെഡ്യൂൾ ചെയ്തത്",
      "inProgress": "പുരോഗതിയിൽ",
      "currentlyWorkingOn": "നിലവിൽ പ്രവർത്തിക്കുന്നു",
      "efficiency": "കാര്യക്ഷമത",
      "thisMonth": "ഈ മാസം",
      "activeTasks": "സജീവ ജോലികൾ",
      "urgent": "അടിയന്തിരം",
      "completed": "പൂർത്തിയായി",
      "toolsReports": "ഉപകരണങ്ങളും റിപ്പോർട്ടുകളും",
      "noActiveTasks": "സജീവ ജോലികൾ ഇല്ല",
      "allCaughtUp": "മികച്ച ജോലി! എല്ലാം പൂർത്തിയായി.",
      "due": "അവസാന തീയതി",
      "noDeadline": "അവസാന തീയതി ഇല്ല",
      "navigate": "നാവിഗേറ്റ് ചെയ്യുക",
      "callCitizen": "പൗരനെ വിളിക്കുക",
      "startWork": "ജോലി ആരംഭിക്കുക",
      "markComplete": "പൂർത്തിയായതായി അടയാളപ്പെടുത്തുക",
      "quickActions": "വേഗത്തിലുള്ള പ്രവർത്തനങ്ങൾ",
      "takeWorkPhoto": "വർക്ക് ഫോട്ടോ എടുക്കുക",
      "submitReport": "റിപ്പോർട്ട് സമർപ്പിക്കുക",
      "contactSupervisor": "സൂപ്പർവൈസറുമായി ബന്ധപ്പെടുക",
      "viewRouteMap": "റൂട്ട് മാപ്പ് കാണുക",
      "progressStats": "പുരോഗതി സ്ഥിതിവിവരക്കണക്കുകൾ",
      "tasksCompleted": "പൂർത്തിയായ ജോലികൾ",
      "avgCompletionTime": "ശരാശരി പൂർത്തീകരണ സമയം (ദിവസങ്ങൾ)",
      "tasksCompletedThisMonth": "ഈ മാസം പൂർത്തിയായ ജോലികൾ",
      "urgentTasksTitle": "അടിയന്തിര ശ്രദ്ധ ആവശ്യമുള്ള അടിയന്തിര ജോലികൾ",
      "noUrgentTasks": "അടിയന്തിര ജോലികൾ ഇല്ല! നന്നായി ചെയ്തു!",
      "asap": "എത്രയും വേഗം",
      "emergencyContact": "അടിയന്തിര ബന്ധപ്പെടൽ",
      "startImmediately": "ഉടനെ ആരംഭിക്കുക",
      "recentlyCompletedTasks": "അടുത്തിടെ പൂർത്തിയായ ജോലികൾ",
      "task": "ജോലി",
      "completedOn": "പൂർത്തിയായത്",
      "recently": "അടുത്തിടെ",
      "viewReport": "റിപ്പോർട്ട് കാണുക",
      "fieldTools": "ഫീൽഡ് ഉപകരണങ്ങൾ",
      "photoDocumentation": "ഫോട്ടോ ഡോക്യുമെന്റേഷൻ",
      "gpsNavigation": "ജിപിഎസ് നാവിഗേഷൻ",
      "workOrderScanner": "വർക്ക് ഓർഡർ സ്കാനർ",
      "incidentReporting": "സംഭവ റിപ്പോർട്ടിംഗ്",
      "reportsAnalytics": "റിപ്പോർട്ടുകളും വിശകലനങ്ങളും",
      "dailyWorkReport": "ദൈനംദിന വർക്ക് റിപ്പോർട്ട്",
      "performanceSummary": "പ്രകടന സംഗ്രഹം",
      "timeTracking": "സമയ ട്രാക്കിംഗ്",
      "completionCertificate": "പൂർത്തീകരണ സർട്ടിഫിക്കറ്റ്"
    },
    "tasks": {
      "title": "പരിചരണ ജോലികൾ",
      "welcomeMessage": "തിരിച്ചുവരവിന് സ്വാഗതം! ഇതാ നിങ്ങളുടെ നിലവിലെ വർക്ക്‌ലോഡ്.",
      "allTasks": "എല്ലാ ജോലികളും",
      "totalTasksAssigned": "മൊത്തം അസൈൻ ചെയ്ത ജോലികൾ",
      "filterByStatus": "സ്ഥിതി അനുസരിച്ച് ഫിൽട്ടർ ചെയ്യുക",
      "clearFilter": "ഫിൽട്ടർ മായ്ക്കുക",
      "filterTasks": "ജോലികൾ ഫിൽട്ടർ ചെയ്യുക",
      "pending": "തീർപ്പുകൽപ്പിക്കാത്തത്",
      "assignedTasks": "അസൈൻ ചെയ്ത ജോലികൾ",
      "overdue": "കാലാവധി കഴിഞ്ഞത്",
      "pastDeadline": "അവസാന തീയതി കഴിഞ്ഞത്",
      "inProgress": "പുരോഗതിയിൽ",
      "activeWork": "സജീവ ജോലി",
      "resolved": "പരിഹരിച്ചു",
      "resolvedTasks": "പരിഹരിച്ച ജോലികൾ",
      "reopened": "വീണ്ടും തുറന്നത്",
      "reopenedTasks": "വീണ്ടും തുറന്ന ജോലികൾ",
      "closed": "അടച്ചത്",
      "closedTasks": "അടച്ച ജോലികൾ",
      "errorLoadingTasks": "ജോലികൾ ലോഡ് ചെയ്യുന്നതിൽ പിശക്",
      "errorMessage": "നിങ്ങളുടെ പരിചരണ ജോലികൾ ലോഡ് ചെയ്യുന്നതിൽ പരാജയപ്പെട്ടു. ദയവായി വീണ്ടും ശ്രമിക്കുക.",
      "totalTasks": "മൊത്തം ജോലികൾ",
      "pendingTasks": "തീർപ്പുകൽപ്പിക്കാത്ത ജോലികൾ",
      "overdueTasks": "കാലാവധി കഴിഞ്ഞ ജോലികൾ",
      "myTasks": "എന്റെ ജോലികൾ",
      "tasksCount": "ജോലികൾ",
      "noOverdueTasks": "കാലാവധി കഴിഞ്ഞ ജോലികൾ ഇല്ല",
      "noPendingTasks": "തീർപ്പുകൽപ്പിക്കാത്ത ജോലികൾ ഇല്ല",
      "noInProgressTasks": "പുരോഗതിയിലുള്ള ജോലികൾ ഇല്ല",
      "noResolvedTasks": "പരിഹരിച്ച ജോലികൾ ഇല്ല",
      "noReopenedTasks": "വീണ്ടും തുറന്ന ജോലികൾ ഇല്ല",
      "noClosedTasks": "അടച്ച ജോലികൾ ഇല്ല",
      "noTasksToShow": "കാണിക്കാൻ ജോലികൾ ഇല്ല",
      "tryDifferentFilter": "മറ്റൊരു ഫിൽട്ടർ പരീക്ഷിക്കുക അല്ലെങ്കിൽ പുതുക്കുക.",
      "estimated": "കണക്കാക്കിയത്",
      "due": "അവസാന തീയതി",
      "opening": "തുറക്കുന്നു...",
      "navigate": "നാവിഗേറ്റ് ചെയ്യുക",
      "photos": "ഫോട്ടോകൾ",
      "uploadNewPhotos": "പുതിയ ഫോട്ടോകൾ അപ്‌ലോഡ് ചെയ്യുക",
      "addPhotos": "ഫോട്ടോകൾ ചേർക്കുക",
      "progress": "പുരോഗതി",
      "workProgressUpdates": "വർക്ക് പുരോഗതിയും അപ്ഡേറ്റുകളും",
      "noUpdatesYet": "ഇതുവരെ അപ്ഡേറ്റുകളോ ഫോട്ടോകളോ ഇല്ല",
      "uploadPhotosAndNotes": "പ്രവർത്തിക്കുമ്പോൾ ഫോട്ടോകൾ അപ്‌ലോഡ് ചെയ്യുകയും പുരോഗതി കുറിപ്പുകൾ ചേർക്കുകയും ചെയ്യുക",
      "workProgressPhoto": "വർക്ക് പുരോഗതി ഫോട്ടോ",
      "uploadedBy": "അപ്‌ലോഡ് ചെയ്തത്",
      "teamMember": "ടീം അംഗം",
      "photo": "ഫോട്ടോ",
      "failedToLoadPhotos": "ഫോട്ടോകൾ ലോഡ് ചെയ്യുന്നതിൽ പരാജയപ്പെട്ടു",
      "startWork": "ജോലി ആരംഭിക്കുക",
      "markAsResolved": "പരിഹരിച്ചതായി അടയാളപ്പെടുത്തുക",
      "markTaskAsResolved": "ജോലി പരിഹരിച്ചതായി അടയാളപ്പെടുത്തുക",
      "completionNotes": "പൂർത്തീകരണ കുറിപ്പുകൾ",
      "addNotesPlaceholder": "പൂർത്തിയായ ജോലിയെക്കുറിച്ച് കുറിപ്പുകൾ ചേർക്കുക...",
      "uploadCompletionPhoto": "പൂർത്തീകരണ ഫോട്ടോ അപ്‌ലോഡ് ചെയ്യുക",
      "photoSelected": "ഫോട്ടോ തിരഞ്ഞെടുത്തു",
      "markResolved": "പരിഹരിച്ചതായി അടയാളപ്പെടുത്തുക",
      "viewExistingPhoto": "നിലവിലുള്ള ഫോട്ടോ കാണുക",
      "estimatedTime": {
        "critical": "2-4 മണിക്കൂർ",
        "high": "4-8 മണിക്കൂർ",
        "medium": "1-2 ദിവസം",
        "low": "2-5 ദിവസം",
        "default": "1-2 ദിവസം"
      }
    }
  },
  "systemSettings": {
    "title": "സിസ്റ്റം കോൺഫിഗറേഷൻ",
    "subtitle": "എല്ലാ സിസ്റ്റം ക്രമീകരണങ്ങളും പ്രവർത്തനക്ഷമമാക്കുക/പ്രവർത്തനരഹിതമാക്കുക നിയന്ത്രണങ്ങളോടെ കൈകാര്യം ചെയ്യുക",
    "searchPlaceholder": "ക്രമീകരണങ്ങൾ തിരയുക...",
    "resetChanges": "മാറ്റങ്ങൾ പുനഃസജ്ജമാക്കുക",
    "saveChanges": "മാറ്റങ്ങൾ സംരക്ഷിക്കുക",
    "refresh": "പുതുക്കുക",
    "loadingSettings": "സിസ്റ്റം ക്രമീകരണങ്ങൾ ലോഡ് ചെയ്യുന്നു...",
    "errorLoadingSettings": "ക്രമീകരണങ്ങൾ ലോഡ് ചെയ്യുന്നതിൽ പിശക്",
    "failedToLoadConfig": "സിസ്റ്റം കോൺഫിഗറേഷൻ ലോഡ് ചെയ്യുന്നതിൽ പരാജയപ്പെട്ടു",
    "tryAgain": "വീണ്ടും ശ്രമിക്കുക",
    "noChanges": "മാറ്റങ്ങളില്ല",
    "noChangesToSave": "സംരക്ഷിക്കാൻ മാറ്റങ്ങളില്ല",
    "settingsSaved": "ക്രമീകരണങ്ങൾ സംരക്ഷിച്ചു",
    "updatedSettings": "{{count}} ക്രമീകരണങ്ങൾ വിജയകരമായി അപ്ഡേറ്റ് ചെയ്തു",
    "saveFailed": "സംരക്ഷണം പരാജയപ്പെട്ടു",
    "failedToSaveSettings": "ക്രമീകരണങ്ങൾ സംരക്ഷിക്കുന്നതിൽ പരാജയപ്പെട്ടു",
    "noSettingsFound": "ക്രമീകരണങ്ങൾ കണ്ടെത്തിയില്ല",
    "adjustSearchTerms": "നിങ്ങളുടെ തിരയൽ പദങ്ങൾ ക്രമീകരിക്കാൻ ശ്രമിക്കുക",
    "settings": "ക്രമീകരണങ്ങൾ",
    "active": "സജീവം",
    "inactive": "നിഷ്‌ക്രിയം",
    "value": "മൂല്യം",
    "key": "കീ",
    "type": "തരം",
    "enabled": "പ്രവർത്തനക്ഷമം",
    "disabled": "പ്രവർത്തനരഹിതം",
    "enterValidJson": "സാധുവായ JSON നൽകുക",
    "enterValue": "{{type}} മൂല്യം നൽകുക",
    "small": "ചെറുത്",
    "medium": "ഇടത്തരം",
    "large": "വലുത്",
    "addNewTranslationKey": "പുതിയ വിവർത്തന കീ ചേർക്കുക",
    "translationKeyAdded": "വിവർത്തന കീ വിജയകരമായി ചേർത്തു",
    "translationKeyExists": "വിവർത്തന കീ ഇതിനകം നിലവിലുണ്ട്",
    "invalidTranslationKey": "അസാധുവായ വിവർത്തന കീ ഫോർമാറ്റ്",
    "translationKeyRequired": "വിവർത്തന കീ ആവശ്യമാണ്",
    "translationValueRequired": "വിവർത്തന മൂല്യം ആവശ്യമാണ്",
    "saveTranslationKey": "വിവർത്തന കീ സംരക്ഷിക്കുക",
    "cancelTranslationKey": "റദ്ദാക്കുക",
    "editTranslationKey": "വിവർത്തന കീ എഡിറ്റ് ചെയ്യുക",
    "deleteTranslationKey": "വിവർത്തന കീ ഇല്ലാതാക്കുക",
    "confirmDeleteTranslationKey": "ഈ വിവർത്തന കീ ഇല്ലാതാക്കാൻ നിങ്ങൾ ആഗ്രഹിക്കുന്നുണ്ടോ?",
    "translationKeyDeleted": "വിവർത്തന കീ വിജയകരമായി ഇല്ലാതാക്കി",
    "failedToDeleteTranslationKey": "വിവർത്തന കീ ഇല്ലാതാക്കുന്നതിൽ പരാജയപ്പെട്ടു",
    "failedToSaveTranslationKey": "വിവർത്തന കീ സംരക്ഷിക്കുന്നതിൽ പരാജയപ്പെട്ടു",
    "translationKeyUpdated": "വിവർത്തന കീ വിജയകരമായി അപ്ഡേറ്റ് ചെയ്തു",
    "failedToUpdateTranslationKey": "വിവർത്തന കീ അപ്ഡേറ്റ് ചെയ്യുന്നതിൽ പരാജയപ്പെട്ടു",
    "sections": {
      "applicationSettings": "ആപ്ലിക്കേഷൻ ക്രമീകരണങ്ങൾ",
      "applicationSettingsDesc": "ആപ്ലിക്കേഷൻ ബ്രാൻഡിംഗും പൊതു ക്രമീകരണങ്ങളും",
      "complaintManagement": "പരാതി മാനേജ്മെന്റ്",
      "complaintManagementDesc": "പരാതി സമർപ്പണവും മാനേജ്മെന്റ് ക്രമീകരണങ്ങളും",
      "geographicSettings": "ഭൂമിശാസ്ത്രപരവും സ്ഥാന ക്രമീകരണങ്ങളും",
      "geographicSettingsDesc": "ഭൂമിശാസ്ത്രപരവും സ്ഥാന-അടിസ്ഥാന കോൺഫിഗറേഷനും",
      "contactInformation": "ബന്ധപ്പെടാനുള്ള വിവരങ്ങൾ",
      "contactInformationDesc": "ബന്ധപ്പെടാനുള്ള വിശദാംശങ്ങളും ഓഫീസ് വിവരങ്ങളും",
      "systemBehavior": "സിസ്റ്റം പെരുമാറ്റം",
      "systemBehaviorDesc": "പ്രധാന സിസ്റ്റം പ്രവർത്തനക്ഷമതയും പെരുമാറ്റവും",
      "notificationCommunication": "അറിയിപ്പും ആശയവിനിമയവും",
      "notificationCommunicationDesc": "അറിയിപ്പ് ക്രമീകരണങ്ങളും ആശയവിനിമയ മുൻഗണനകളും",
      "systemDataStructures": "സിസ്റ്റം ഡാറ്റ ഘടനകൾ",
      "systemDataStructuresDesc": "സിസ്റ്റം ഡാറ്റ ഘടനകളും കോൺഫിഗറേഷനുകളും"
    },
    "labels": {
      "appName": "ആപ്ലിക്കേഷൻ പേര്",
      "logoUrl": "ലോഗോ URL",
      "logoSize": "ലോഗോ വലുപ്പം",
      "adminEmail": "അഡ്മിനിസ്ട്രേറ്റർ ഇമെയിൽ",
      "complaintIdPrefix": "പരാതി ഐഡി പ്രിഫിക്സ്",
      "idStartNumber": "ഐഡി ആരംഭ നമ്പർ",
      "idNumberLength": "ഐഡി നമ്പർ നീളം",
      "maxPhotoSize": "പരമാവധി ഫോട്ടോ വലുപ്പം (MB)",
      "maxPhotoCount": "പരമാവധി ഫോട്ടോ എണ്ണം",
      "dailyComplaintLimit": "ദൈനംദിന പരാതി പരിധി",
      "enableDailyLimit": "ദൈനംദിന പരിധി പ്രവർത്തനക്ഷമമാക്കുക",
      "allowGuestComplaints": "അതിഥി പരാതികൾ അനുവദിക്കുക",
      "defaultSlaHours": "ഡിഫോൾട്ട് SLA മണിക്കൂറുകൾ",
      "searchPlaceContext": "സ്ഥലം തിരയൽ സന്ദർഭം",
      "countryCodes": "രാജ്യ കോഡുകൾ (ISO2)",
      "defaultLatitude": "ഡിഫോൾട്ട് അക്ഷാംശം",
      "defaultLongitude": "ഡിഫോൾട്ട് രേഖാംശം",
      "boundingBoxNorth": "ബൗണ്ടിംഗ് ബോക്സ് വടക്ക്",
      "boundingBoxSouth": "ബൗണ്ടിംഗ് ബോക്സ് തെക്ക്",
      "boundingBoxEast": "ബൗണ്ടിംഗ് ബോക്സ് കിഴക്ക്",
      "boundingBoxWest": "ബൗണ്ടിംഗ് ബോക്സ് പടിഞ്ഞാറ്",
      "serviceAreaBoundary": "സേവന മേഖല അതിർത്തി (GeoJSON)",
      "enableLocationValidation": "സ്ഥാന സാധൂകരണം പ്രവർത്തനക്ഷമമാക്കുക",
      "helplineNumber": "ഹെൽപ്പ്‌ലൈൻ നമ്പർ",
      "supportEmail": "പിന്തുണ ഇമെയിൽ",
      "officeHours": "ഓഫീസ് സമയം",
      "officeAddress": "ഓഫീസ് വിലാസം",
      "autoAssignComplaints": "പരാതികൾ സ്വയമേവ അസൈൻ ചെയ്യുക",
      "allowCitizenRegistration": "പൗര രജിസ്ട്രേഷൻ അനുവദിക്കുക",
      "otpExpiryMinutes": "OTP കാലാവധി മിനിറ്റുകൾ",
      "maxFileSize": "പരമാവധി ഫയൽ വലുപ്പം (MB)",
      "notificationConfig": "അറിയിപ്പ് കോൺഫിഗറേഷൻ (JSON)",
      "complaintPriorities": "പരാതി മുൻഗണനകൾ (JSON)",
      "complaintStatuses": "പരാതി നിലകൾ (JSON)"
    }
  }
}